{"regions":[{"categoryCode":null,"masterCode":null,"code":"24010001","name":"24010001"},{"categoryCode":null,"masterCode":null,"code":"24010002","name":"24010002"},{"categoryCode":null,"masterCode":null,"code":"24010003","name":"24010003"},{"categoryCode":null,"masterCode":null,"code":"24010004","name":"24010004"},{"categoryCode":null,"masterCode":null,"code":"24010005","name":"24010005"},{"categoryCode":null,"masterCode":null,"code":"24010006","name":"24010006"},{"categoryCode":null,"masterCode":null,"code":"24010007","name":"24010007"},{"categoryCode":null,"masterCode":null,"code":"24010008","name":"24010008"}]}