{"regions":[{"categoryCode":null,"masterCode":null,"code":"56240123","name":"56240123"},{"categoryCode":null,"masterCode":null,"code":"56240124","name":"56240124"},{"categoryCode":null,"masterCode":null,"code":"56240125","name":"56240125"},{"categoryCode":null,"masterCode":null,"code":"56240126","name":"56240126"},{"categoryCode":null,"masterCode":null,"code":"56240127","name":"56240127"},{"categoryCode":null,"masterCode":null,"code":"56240128","name":"56240128"},{"categoryCode":null,"masterCode":null,"code":"56240129","name":"56240129"},{"categoryCode":null,"masterCode":null,"code":"56240130","name":"56240130"},{"categoryCode":null,"masterCode":null,"code":"56240131","name":"56240131"},{"categoryCode":null,"masterCode":null,"code":"56240132","name":"56240132"},{"categoryCode":null,"masterCode":null,"code":"56240133","name":"56240133"},{"categoryCode":null,"masterCode":null,"code":"56240134","name":"56240134"},{"categoryCode":null,"masterCode":null,"code":"56240135","name":"56240135"},{"categoryCode":null,"masterCode":null,"code":"56240136","name":"56240136"},{"categoryCode":null,"masterCode":null,"code":"56240137","name":"56240137"},{"categoryCode":null,"masterCode":null,"code":"56240138","name":"56240138"},{"categoryCode":null,"masterCode":null,"code":"56240139","name":"56240139"},{"categoryCode":null,"masterCode":null,"code":"56240140","name":"56240140"},{"categoryCode":null,"masterCode":null,"code":"56240141","name":"56240141"},{"categoryCode":null,"masterCode":null,"code":"56240142","name":"56240142"},{"categoryCode":null,"masterCode":null,"code":"56240143","name":"56240143"}]}