{"regions":[{"categoryCode":"5","masterCode":"5406000","code":"5406001","name":"ANON"},{"categoryCode":"5","masterCode":"5406000","code":"5406002","name":"APALIT"},{"categoryCode":"5","masterCode":"5406000","code":"5406003","name":"BASA AIR BASE"},{"categoryCode":"5","masterCode":"5406000","code":"5406004","name":"BENEDICTO"},{"categoryCode":"5","masterCode":"5406000","code":"5406005","name":"BODEGA"},{"categoryCode":"5","masterCode":"5406000","code":"5406006","name":"CABANGCALAN"},{"categoryCode":"5","masterCode":"5406000","code":"5406007","name":"CALANTAS"},{"categoryCode":"5","masterCode":"5406000","code":"5406008","name":"CARMENCITA"},{"categoryCode":"5","masterCode":"5406000","code":"5406009","name":"CONSUELO"},{"categoryCode":"5","masterCode":"5406000","code":"5406010","name":"DAMPE"},{"categoryCode":"5","masterCode":"5406000","code":"5406011","name":"DEL CARMEN"},{"categoryCode":"5","masterCode":"5406000","code":"5406012","name":"FORTUNA"},{"categoryCode":"5","masterCode":"5406000","code":"5406013","name":"GUTAD"},{"categoryCode":"5","masterCode":"5406000","code":"5406014","name":"MABICAL"},{"categoryCode":"5","masterCode":"5406000","code":"5406015","name":"STO. ROSARIO"},{"categoryCode":"5","masterCode":"5406000","code":"5406016","name":"MALIGAYA"},{"categoryCode":"5","masterCode":"5406000","code":"5406017","name":"NABUCLOD"},{"categoryCode":"5","masterCode":"5406000","code":"5406018","name":"PABANLAG"},{"categoryCode":"5","masterCode":"5406000","code":"5406019","name":"PAGUIRUAN"},{"categoryCode":"5","masterCode":"5406000","code":"5406020","name":"PALMAYO"},{"categoryCode":"5","masterCode":"5406000","code":"5406021","name":"PANDAGUIRIG"},{"categoryCode":"5","masterCode":"5406000","code":"5406023","name":"POBLACION"},{"categoryCode":"5","masterCode":"5406000","code":"5406024","name":"SAN ANTONIO"},{"categoryCode":"5","masterCode":"5406000","code":"5406025","name":"SAN ISIDRO"},{"categoryCode":"5","masterCode":"5406000","code":"5406026","name":"SAN JOSE"},{"categoryCode":"5","masterCode":"5406000","code":"5406027","name":"SAN NICOLAS"},{"categoryCode":"5","masterCode":"5406000","code":"5406028","name":"SAN PEDRO"},{"categoryCode":"5","masterCode":"5406000","code":"5406029","name":"SAN RAMON"},{"categoryCode":"5","masterCode":"5406000","code":"5406030","name":"SAN ROQUE"},{"categoryCode":"5","masterCode":"5406000","code":"5406031","name":"STA. MONICA"},{"categoryCode":"5","masterCode":"5406000","code":"5406032","name":"SOLIB"},{"categoryCode":"5","masterCode":"5406000","code":"5406033","name":"VALDEZ"},{"categoryCode":"5","masterCode":"5406000","code":"5406034","name":"MAWACAT"}]}