{"regions":[{"categoryCode":null,"masterCode":null,"code":"21030061","name":"21030061"},{"categoryCode":null,"masterCode":null,"code":"21030062","name":"21030062"},{"categoryCode":null,"masterCode":null,"code":"21030063","name":"21030063"},{"categoryCode":null,"masterCode":null,"code":"21030064","name":"21030064"},{"categoryCode":null,"masterCode":null,"code":"21030065","name":"21030065"},{"categoryCode":null,"masterCode":null,"code":"21030066","name":"21030066"},{"categoryCode":null,"masterCode":null,"code":"21030067","name":"21030067"},{"categoryCode":null,"masterCode":null,"code":"21030068","name":"21030068"},{"categoryCode":null,"masterCode":null,"code":"21030069","name":"21030069"}]}