{"regions":[{"categoryCode":null,"masterCode":null,"code":"56300049","name":"56300049"},{"categoryCode":null,"masterCode":null,"code":"56300050","name":"56300050"},{"categoryCode":null,"masterCode":null,"code":"56300051","name":"56300051"},{"categoryCode":null,"masterCode":null,"code":"56300052","name":"56300052"},{"categoryCode":null,"masterCode":null,"code":"56300053","name":"56300053"},{"categoryCode":null,"masterCode":null,"code":"56300054","name":"56300054"},{"categoryCode":null,"masterCode":null,"code":"56300055","name":"56300055"}]}