{"regions":[{"categoryCode":"5","masterCode":"4320000","code":"4320001","name":"DON PEDRO"},{"categoryCode":"5","masterCode":"4320000","code":"4320002","name":"LINANGKAYAN"},{"categoryCode":"5","masterCode":"4320000","code":"4320003","name":"LUBILAN"},{"categoryCode":"5","masterCode":"4320000","code":"4320004","name":"MAPULOG"},{"categoryCode":"5","masterCode":"4320000","code":"4320005","name":"MAPUTI"},{"categoryCode":"5","masterCode":"4320000","code":"4320006","name":"MAT-I"},{"categoryCode":"5","masterCode":"4320000","code":"4320007","name":"PATAG"},{"categoryCode":"5","masterCode":"4320000","code":"4320008","name":"POBLACION"},{"categoryCode":"5","masterCode":"4320000","code":"4320009","name":"TAGBALOGO"},{"categoryCode":"5","masterCode":"4320000","code":"4320010","name":"TUBORAN"}]}