{"regions":[{"categoryCode":"5","masterCode":"0615000","code":"0615001","name":"ABIERA"},{"categoryCode":"5","masterCode":"0615000","code":"0615002","name":"AGUILA"},{"categoryCode":"5","masterCode":"0615000","code":"0615003","name":"ALEGRE"},{"categoryCode":"5","masterCode":"0615000","code":"0615004","name":"ARAS-ASAN"},{"categoryCode":"5","masterCode":"0615000","code":"0615005","name":"BACALAN"},{"categoryCode":"5","masterCode":"0615000","code":"0615006","name":"CALLAN"},{"categoryCode":"5","masterCode":"0615000","code":"0615007","name":"NAUHON"},{"categoryCode":"5","masterCode":"0615000","code":"0615008","name":"P. JAVIER "},{"categoryCode":"5","masterCode":"0615000","code":"0615009","name":"POBLACION"},{"categoryCode":"5","masterCode":"0615000","code":"0615010","name":"IDIO"}]}