{"regions":[{"categoryCode":"5","masterCode":"3747000","code":"3747006","name":"BARANGAY 2"},{"categoryCode":"5","masterCode":"3747000","code":"3747008","name":"NULA-TULA"},{"categoryCode":"5","masterCode":"3747000","code":"3747010","name":"LIBERTAD"},{"categoryCode":"5","masterCode":"3747000","code":"3747011","name":"BARANGAY 5"},{"categoryCode":"5","masterCode":"3747000","code":"3747012","name":"BARANGAY 6"},{"categoryCode":"5","masterCode":"3747000","code":"3747013","name":"BARANGAY 6-A"},{"categoryCode":"5","masterCode":"3747000","code":"3747014","name":"BARANGAY 7"},{"categoryCode":"5","masterCode":"3747000","code":"3747015","name":"BARANGAY 8"},{"categoryCode":"5","masterCode":"3747000","code":"3747018","name":"BARANGAY 100"},{"categoryCode":"5","masterCode":"3747000","code":"3747019","name":"BARANGAY 101"},{"categoryCode":"5","masterCode":"3747000","code":"3747020","name":"BARANGAY 102"},{"categoryCode":"5","masterCode":"3747000","code":"3747021","name":"BARANGAY 103"},{"categoryCode":"5","masterCode":"3747000","code":"3747022","name":"BARANGAY 103-A"},{"categoryCode":"5","masterCode":"3747000","code":"3747023","name":"BARANGAY 104"},{"categoryCode":"5","masterCode":"3747000","code":"3747024","name":"BARANGAY 105"},{"categoryCode":"5","masterCode":"3747000","code":"3747025","name":"BARANGAY 106"},{"categoryCode":"5","masterCode":"3747000","code":"3747026","name":"BARANGAY 107"},{"categoryCode":"5","masterCode":"3747000","code":"3747027","name":"BARANGAY 108"},{"categoryCode":"5","masterCode":"3747000","code":"3747032","name":"BARANGAY 12"},{"categoryCode":"5","masterCode":"3747000","code":"3747034","name":"BARANGAY 13"},{"categoryCode":"5","masterCode":"3747000","code":"3747035","name":"BARANGAY 14"},{"categoryCode":"5","masterCode":"3747000","code":"3747036","name":"BARANGAY 15"},{"categoryCode":"5","masterCode":"3747000","code":"3747037","name":"BARANGAY 16"},{"categoryCode":"5","masterCode":"3747000","code":"3747038","name":"BARANGAY 17"},{"categoryCode":"5","masterCode":"3747000","code":"3747039","name":"BARANGAY 18"},{"categoryCode":"5","masterCode":"3747000","code":"3747040","name":"BARANGAY 19"},{"categoryCode":"5","masterCode":"3747000","code":"3747041","name":"BARANGAY 20"},{"categoryCode":"5","masterCode":"3747000","code":"3747042","name":"BARANGAY 21"},{"categoryCode":"5","masterCode":"3747000","code":"3747043","name":"BARANGAY 21-A"},{"categoryCode":"5","masterCode":"3747000","code":"3747044","name":"BARANGAY 22"},{"categoryCode":"5","masterCode":"3747000","code":"3747045","name":"BARANGAY 23"},{"categoryCode":"5","masterCode":"3747000","code":"3747046","name":"BARANGAY 24"},{"categoryCode":"5","masterCode":"3747000","code":"3747047","name":"BARANGAY 25"},{"categoryCode":"5","masterCode":"3747000","code":"3747048","name":"BARANGAY 26"},{"categoryCode":"5","masterCode":"3747000","code":"3747049","name":"BARANGAY 27"},{"categoryCode":"5","masterCode":"3747000","code":"3747050","name":"BARANGAY 28"},{"categoryCode":"5","masterCode":"3747000","code":"3747051","name":"BARANGAY 29"},{"categoryCode":"5","masterCode":"3747000","code":"3747052","name":"BARANGAY 30"},{"categoryCode":"5","masterCode":"3747000","code":"3747053","name":"BARANGAY 31"},{"categoryCode":"5","masterCode":"3747000","code":"3747054","name":"BARANGAY 32"},{"categoryCode":"5","masterCode":"3747000","code":"3747055","name":"BARANGAY 33"},{"categoryCode":"5","masterCode":"3747000","code":"3747056","name":"BARANGAY 34"},{"categoryCode":"5","masterCode":"3747000","code":"3747057","name":"BARANGAY 35"},{"categoryCode":"5","masterCode":"3747000","code":"3747058","name":"BARANGAY 35-A"},{"categoryCode":"5","masterCode":"3747000","code":"3747059","name":"BARANGAY 36"},{"categoryCode":"5","masterCode":"3747000","code":"3747060","name":"BARANGAY 37"},{"categoryCode":"5","masterCode":"3747000","code":"3747061","name":"BARANGAY 37-A"},{"categoryCode":"5","masterCode":"3747000","code":"3747062","name":"BARANGAY 38"},{"categoryCode":"5","masterCode":"3747000","code":"3747063","name":"BARANGAY 39"},{"categoryCode":"5","masterCode":"3747000","code":"3747064","name":"BARANGAY 40"},{"categoryCode":"5","masterCode":"3747000","code":"3747065","name":"BARANGAY 41"},{"categoryCode":"5","masterCode":"3747000","code":"3747066","name":"BARANGAY 42"},{"categoryCode":"5","masterCode":"3747000","code":"3747067","name":"BARANGAY 43"},{"categoryCode":"5","masterCode":"3747000","code":"3747068","name":"BARANGAY 43-A"},{"categoryCode":"5","masterCode":"3747000","code":"3747069","name":"BARANGAY 43-B"},{"categoryCode":"5","masterCode":"3747000","code":"3747070","name":"BARANGAY 44"},{"categoryCode":"5","masterCode":"3747000","code":"3747071","name":"BARANGAY 44-A"},{"categoryCode":"5","masterCode":"3747000","code":"3747072","name":"BARANGAY 45"},{"categoryCode":"5","masterCode":"3747000","code":"3747073","name":"BARANGAY 46"},{"categoryCode":"5","masterCode":"3747000","code":"3747074","name":"BARANGAY 47"},{"categoryCode":"5","masterCode":"3747000","code":"3747075","name":"BARANGAY 48"},{"categoryCode":"5","masterCode":"3747000","code":"3747076","name":"BARANGAY 49"},{"categoryCode":"5","masterCode":"3747000","code":"3747077","name":"BARANGAY 50"},{"categoryCode":"5","masterCode":"3747000","code":"3747078","name":"BARANGAY 50-A"},{"categoryCode":"5","masterCode":"3747000","code":"3747079","name":"BARANGAY 50-B"},{"categoryCode":"5","masterCode":"3747000","code":"3747080","name":"BARANGAY 51"},{"categoryCode":"5","masterCode":"3747000","code":"3747081","name":"BARANGAY 52"},{"categoryCode":"5","masterCode":"3747000","code":"3747082","name":"BARANGAY 53"},{"categoryCode":"5","masterCode":"3747000","code":"3747083","name":"BARANGAY 54"},{"categoryCode":"5","masterCode":"3747000","code":"3747084","name":"EL REPOSO"},{"categoryCode":"5","masterCode":"3747000","code":"3747085","name":"BARANGAY 56"},{"categoryCode":"5","masterCode":"3747000","code":"3747086","name":"BARANGAY 57"},{"categoryCode":"5","masterCode":"3747000","code":"3747087","name":"BARANGAY 58"},{"categoryCode":"5","masterCode":"3747000","code":"3747088","name":"BARANGAY 59"},{"categoryCode":"5","masterCode":"3747000","code":"3747089","name":"BARANGAY 60"},{"categoryCode":"5","masterCode":"3747000","code":"3747090","name":"BARANGAY 60-A"},{"categoryCode":"5","masterCode":"3747000","code":"3747091","name":"BARANGAY 61"},{"categoryCode":"5","masterCode":"3747000","code":"3747092","name":"BARANGAY 62"},{"categoryCode":"5","masterCode":"3747000","code":"3747093","name":"BARANGAY 63"},{"categoryCode":"5","masterCode":"3747000","code":"3747094","name":"BARANGAY 64"},{"categoryCode":"5","masterCode":"3747000","code":"3747095","name":"BARANGAY 65"},{"categoryCode":"5","masterCode":"3747000","code":"3747096","name":"BARANGAY 66"},{"categoryCode":"5","masterCode":"3747000","code":"3747097","name":"BARANGAY 66-A"},{"categoryCode":"5","masterCode":"3747000","code":"3747098","name":"BARANGAY 67"},{"categoryCode":"5","masterCode":"3747000","code":"3747099","name":"BARANGAY 68"},{"categoryCode":"5","masterCode":"3747000","code":"3747100","name":"BARANGAY 69"},{"categoryCode":"5","masterCode":"3747000","code":"3747101","name":"BARANGAY 70"},{"categoryCode":"5","masterCode":"3747000","code":"3747102","name":"BARANGAY 71"},{"categoryCode":"5","masterCode":"3747000","code":"3747103","name":"BARANGAY 72"},{"categoryCode":"5","masterCode":"3747000","code":"3747104","name":"BARANGAY 73"},{"categoryCode":"5","masterCode":"3747000","code":"3747105","name":"BARANGAY 74"},{"categoryCode":"5","masterCode":"3747000","code":"3747106","name":"BARANGAY 75"},{"categoryCode":"5","masterCode":"3747000","code":"3747107","name":"BARANGAY 76"},{"categoryCode":"5","masterCode":"3747000","code":"3747108","name":"BARANGAY 77"},{"categoryCode":"5","masterCode":"3747000","code":"3747109","name":"BARANGAY 78"},{"categoryCode":"5","masterCode":"3747000","code":"3747110","name":"BARANGAY 79"},{"categoryCode":"5","masterCode":"3747000","code":"3747112","name":"BARANGAY 80"},{"categoryCode":"5","masterCode":"3747000","code":"3747113","name":"BARANGAY 81"},{"categoryCode":"5","masterCode":"3747000","code":"3747114","name":"BARANGAY 82"},{"categoryCode":"5","masterCode":"3747000","code":"3747115","name":"BARANGAY 83"},{"categoryCode":"5","masterCode":"3747000","code":"3747116","name":"BARANGAY 83-A"},{"categoryCode":"5","masterCode":"3747000","code":"3747117","name":"BARANGAY 84"},{"categoryCode":"5","masterCode":"3747000","code":"3747118","name":"BARANGAY 85"},{"categoryCode":"5","masterCode":"3747000","code":"3747119","name":"BARANGAY 86"},{"categoryCode":"5","masterCode":"3747000","code":"3747120","name":"BARANGAY 87"},{"categoryCode":"5","masterCode":"3747000","code":"3747121","name":"BARANGAY 88"},{"categoryCode":"5","masterCode":"3747000","code":"3747122","name":"BARANGAY 89"},{"categoryCode":"5","masterCode":"3747000","code":"3747123","name":"BARANGAY 90"},{"categoryCode":"5","masterCode":"3747000","code":"3747124","name":"BARANGAY 91"},{"categoryCode":"5","masterCode":"3747000","code":"3747125","name":"BARANGAY 92"},{"categoryCode":"5","masterCode":"3747000","code":"3747127","name":"BARANGAY 93"},{"categoryCode":"5","masterCode":"3747000","code":"3747128","name":"BARANGAY 94"},{"categoryCode":"5","masterCode":"3747000","code":"3747129","name":"BARANGAY 95"},{"categoryCode":"5","masterCode":"3747000","code":"3747130","name":"BARANGAY 96"},{"categoryCode":"5","masterCode":"3747000","code":"3747131","name":"BARANGAY 97"},{"categoryCode":"5","masterCode":"3747000","code":"3747132","name":"BARANGAY 98"},{"categoryCode":"5","masterCode":"3747000","code":"3747133","name":"BARANGAY 99"},{"categoryCode":"5","masterCode":"3747000","code":"3747134","name":"BARANGAY 109"},{"categoryCode":"5","masterCode":"3747000","code":"3747135","name":"BARANGAY 109-A"},{"categoryCode":"5","masterCode":"3747000","code":"3747136","name":"BARANGAY 110"},{"categoryCode":"5","masterCode":"3747000","code":"3747137","name":"BARANGAY 5-A"},{"categoryCode":"5","masterCode":"3747000","code":"3747138","name":"BARANGAY 36-A"},{"categoryCode":"5","masterCode":"3747000","code":"3747139","name":"BARANGAY 42-A"},{"categoryCode":"5","masterCode":"3747000","code":"3747140","name":"BARANGAY 48-A"},{"categoryCode":"5","masterCode":"3747000","code":"3747141","name":"BARANGAY 48-B"},{"categoryCode":"5","masterCode":"3747000","code":"3747142","name":"BARANGAY 51-A"},{"categoryCode":"5","masterCode":"3747000","code":"3747143","name":"BARANGAY 54-A"},{"categoryCode":"5","masterCode":"3747000","code":"3747145","name":"BARANGAY 56-A"},{"categoryCode":"5","masterCode":"3747000","code":"3747146","name":"BARANGAY 59-A"},{"categoryCode":"5","masterCode":"3747000","code":"3747147","name":"BARANGAY 59-B"},{"categoryCode":"5","masterCode":"3747000","code":"3747148","name":"BARANGAY 62-A"},{"categoryCode":"5","masterCode":"3747000","code":"3747149","name":"BARANGAY 62-B"},{"categoryCode":"5","masterCode":"3747000","code":"3747150","name":"BARANGAY 83-B"},{"categoryCode":"5","masterCode":"3747000","code":"3747151","name":"BARANGAY 83-C"},{"categoryCode":"5","masterCode":"3747000","code":"3747152","name":"BARANGAY 95-A"},{"categoryCode":"5","masterCode":"3747000","code":"3747153","name":"BARANGAY 8-A"},{"categoryCode":"5","masterCode":"3747000","code":"3747154","name":"BARANGAY 23-A"},{"categoryCode":"5","masterCode":"3747000","code":"3747155","name":"BARANGAY 94-A"}]}