{"regions":[{"categoryCode":"5","masterCode":"3728000","code":"3728001","name":"BAGACAY EAST"},{"categoryCode":"5","masterCode":"3728000","code":"3728002","name":"BAGACAY WEST"},{"categoryCode":"5","masterCode":"3728000","code":"3728003","name":"BONGTOD"},{"categoryCode":"5","masterCode":"3728000","code":"3728004","name":"BOCAWON "},{"categoryCode":"5","masterCode":"3728000","code":"3728005","name":"BURACAN"},{"categoryCode":"5","masterCode":"3728000","code":"3728006","name":"CAABANGAN "},{"categoryCode":"5","masterCode":"3728000","code":"3728007","name":"CACAO"},{"categoryCode":"5","masterCode":"3728000","code":"3728008","name":"CAGNGARAN"},{"categoryCode":"5","masterCode":"3728000","code":"3728009","name":"CALABNIAN"},{"categoryCode":"5","masterCode":"3728000","code":"3728010","name":"CALAGHUSAN"},{"categoryCode":"5","masterCode":"3728000","code":"3728011","name":"CALTAYAN"},{"categoryCode":"5","masterCode":"3728000","code":"3728012","name":"CANBAÑEZ"},{"categoryCode":"5","masterCode":"3728000","code":"3728013","name":"COGON"},{"categoryCode":"5","masterCode":"3728000","code":"3728014","name":"DUYOG"},{"categoryCode":"5","masterCode":"3728000","code":"3728015","name":"GIMIRANAT EAST"},{"categoryCode":"5","masterCode":"3728000","code":"3728016","name":"GIMIRANAT WEST"},{"categoryCode":"5","masterCode":"3728000","code":"3728017","name":"LIMBA"},{"categoryCode":"5","masterCode":"3728000","code":"3728018","name":"LUBI-LUBI"},{"categoryCode":"5","masterCode":"3728000","code":"3728019","name":"LUNETA"},{"categoryCode":"5","masterCode":"3728000","code":"3728020","name":"MAG-ASO"},{"categoryCode":"5","masterCode":"3728000","code":"3728021","name":"MOROBORO"},{"categoryCode":"5","masterCode":"3728000","code":"3728022","name":"PANSUD"},{"categoryCode":"5","masterCode":"3728000","code":"3728023","name":"PAWA"},{"categoryCode":"5","masterCode":"3728000","code":"3728024","name":"PILIWAY"},{"categoryCode":"5","masterCode":"3728000","code":"3728025","name":"POBLACION DISTRICT 1"},{"categoryCode":"5","masterCode":"3728000","code":"3728026","name":"POBLACION DISTRICT 2"},{"categoryCode":"5","masterCode":"3728000","code":"3728027","name":"POBLACION DISTRICT 3"},{"categoryCode":"5","masterCode":"3728000","code":"3728028","name":"POBLACION DISTRICT 4"},{"categoryCode":"5","masterCode":"3728000","code":"3728029","name":"QUIONG"},{"categoryCode":"5","masterCode":"3728000","code":"3728030","name":"RIZAL"},{"categoryCode":"5","masterCode":"3728000","code":"3728031","name":"SAN VICTORAY"},{"categoryCode":"5","masterCode":"3728000","code":"3728032","name":"SANTA ANA"},{"categoryCode":"5","masterCode":"3728000","code":"3728033","name":"SANTA ELENA"},{"categoryCode":"5","masterCode":"3728000","code":"3728034","name":"TABANG"},{"categoryCode":"5","masterCode":"3728000","code":"3728035","name":"TARUGAN"}]}