{"regions":[{"categoryCode":"5","masterCode":"5801000","code":"5801001","name":"BAGUMBAYAN"},{"categoryCode":"5","masterCode":"5801000","code":"5801005","name":"KALAYAAN"},{"categoryCode":"5","masterCode":"5801000","code":"5801007","name":"POBLACION IBABA"},{"categoryCode":"5","masterCode":"5801000","code":"5801008","name":"POBLACION ITAAS"},{"categoryCode":"5","masterCode":"5801000","code":"5801009","name":"SAN ISIDRO"},{"categoryCode":"5","masterCode":"5801000","code":"5801010","name":"SAN PEDRO"},{"categoryCode":"5","masterCode":"5801000","code":"5801011","name":"SAN ROQUE"},{"categoryCode":"5","masterCode":"5801000","code":"5801012","name":"SAN VICENTE"},{"categoryCode":"5","masterCode":"5801000","code":"5801013","name":"SANTO NIÑO"},{"categoryCode":"5","masterCode":"5801000","code":"5801014","name":"MAHABANG PARANG"}]}