{"regions":[{"categoryCode":null,"masterCode":null,"code":"69040075","name":"69040075"},{"categoryCode":null,"masterCode":null,"code":"69040076","name":"69040076"},{"categoryCode":null,"masterCode":null,"code":"69040077","name":"69040077"},{"categoryCode":null,"masterCode":null,"code":"69040078","name":"69040078"},{"categoryCode":null,"masterCode":null,"code":"69040079","name":"69040079"},{"categoryCode":null,"masterCode":null,"code":"69040080","name":"69040080"},{"categoryCode":null,"masterCode":null,"code":"69040081","name":"69040081"},{"categoryCode":null,"masterCode":null,"code":"69040082","name":"69040082"}]}