{"regions":[{"categoryCode":"5","masterCode":"3606000","code":"3606002","name":"BAGOAINGUD"},{"categoryCode":"5","masterCode":"3606000","code":"3606003","name":"BANSAYAN"},{"categoryCode":"5","masterCode":"3606000","code":"3606004","name":"BASINGAN"},{"categoryCode":"5","masterCode":"3606000","code":"3606005","name":"BATANGAN"},{"categoryCode":"5","masterCode":"3606000","code":"3606006","name":"BUALAN"},{"categoryCode":"5","masterCode":"3606000","code":"3606007","name":"POBLACION"},{"categoryCode":"5","masterCode":"3606000","code":"3606008","name":"BUBONGA DIDAGUN"},{"categoryCode":"5","masterCode":"3606000","code":"3606011","name":"CARIGONGAN"},{"categoryCode":"5","masterCode":"3606000","code":"3606012","name":"BACOLOD"},{"categoryCode":"5","masterCode":"3606000","code":"3606014","name":"DILABAYAN"},{"categoryCode":"5","masterCode":"3606000","code":"3606015","name":"DIMAPATOY"},{"categoryCode":"5","masterCode":"3606000","code":"3606017","name":"DIMAYON PROPER"},{"categoryCode":"5","masterCode":"3606000","code":"3606019","name":"DIOLANGAN"},{"categoryCode":"5","masterCode":"3606000","code":"3606022","name":"GUIGUIKUN"},{"categoryCode":"5","masterCode":"3606000","code":"3606023","name":"DIBAROSAN"},{"categoryCode":"5","masterCode":"3606000","code":"3606027","name":"MADANDING"},{"categoryCode":"5","masterCode":"3606000","code":"3606028","name":"MALUNGUN"},{"categoryCode":"5","masterCode":"3606000","code":"3606030","name":"MASOROT"},{"categoryCode":"5","masterCode":"3606000","code":"3606031","name":"MATAMPAY DIMARAO"},{"categoryCode":"5","masterCode":"3606000","code":"3606032","name":"MIABALAWAG"},{"categoryCode":"5","masterCode":"3606000","code":"3606033","name":"MONTIAAN"},{"categoryCode":"5","masterCode":"3606000","code":"3606035","name":"PAGAYAWAN"},{"categoryCode":"5","masterCode":"3606000","code":"3606037","name":"PALAO"},{"categoryCode":"5","masterCode":"3606000","code":"3606038","name":"PANALAWAN "},{"categoryCode":"5","masterCode":"3606000","code":"3606039","name":"PANTAR "},{"categoryCode":"5","masterCode":"3606000","code":"3606041","name":"PENDOGOAN"},{"categoryCode":"5","masterCode":"3606000","code":"3606045","name":"POLAYAGAN"},{"categoryCode":"5","masterCode":"3606000","code":"3606048","name":"RAMAIN BUBONG"},{"categoryCode":"5","masterCode":"3606000","code":"3606049","name":"ROGERO"},{"categoryCode":"5","masterCode":"3606000","code":"3606051","name":"SALIPONGAN"},{"categoryCode":"5","masterCode":"3606000","code":"3606052","name":"SUNGGOD"},{"categoryCode":"5","masterCode":"3606000","code":"3606053","name":"TABORO"},{"categoryCode":"5","masterCode":"3606000","code":"3606054","name":"DALAON"},{"categoryCode":"5","masterCode":"3606000","code":"3606058","name":"DIMAYON"},{"categoryCode":"5","masterCode":"3606000","code":"3606059","name":"PINDOLONAN"},{"categoryCode":"5","masterCode":"3606000","code":"3606060","name":"PUNUD"}]}