{"regions":[{"categoryCode":"5","masterCode":"4201000","code":"4201001","name":"BALINTONGA"},{"categoryCode":"5","masterCode":"4201000","code":"4201002","name":"BANISILON"},{"categoryCode":"5","masterCode":"4201000","code":"4201003","name":"BURGOS"},{"categoryCode":"5","masterCode":"4201000","code":"4201004","name":"CALUBE"},{"categoryCode":"5","masterCode":"4201000","code":"4201005","name":"CAPUTOL"},{"categoryCode":"5","masterCode":"4201000","code":"4201006","name":"CASUSAN"},{"categoryCode":"5","masterCode":"4201000","code":"4201007","name":"CONAT"},{"categoryCode":"5","masterCode":"4201000","code":"4201008","name":"CULPAN"},{"categoryCode":"5","masterCode":"4201000","code":"4201009","name":"DALISAY"},{"categoryCode":"5","masterCode":"4201000","code":"4201010","name":"DULLAN"},{"categoryCode":"5","masterCode":"4201000","code":"4201011","name":"IBABAO"},{"categoryCode":"5","masterCode":"4201000","code":"4201012","name":"TUBOD"},{"categoryCode":"5","masterCode":"4201000","code":"4201013","name":"LABO"},{"categoryCode":"5","masterCode":"4201000","code":"4201014","name":"LAWA-AN"},{"categoryCode":"5","masterCode":"4201000","code":"4201015","name":"LOBOGON"},{"categoryCode":"5","masterCode":"4201000","code":"4201016","name":"LUMBAYAO"},{"categoryCode":"5","masterCode":"4201000","code":"4201017","name":"MAKAWA"},{"categoryCode":"5","masterCode":"4201000","code":"4201018","name":"MANAMONG"},{"categoryCode":"5","masterCode":"4201000","code":"4201019","name":"MATIPAZ"},{"categoryCode":"5","masterCode":"4201000","code":"4201020","name":"MAULAR"},{"categoryCode":"5","masterCode":"4201000","code":"4201021","name":"MITAZAN"},{"categoryCode":"5","masterCode":"4201000","code":"4201022","name":"MOHON"},{"categoryCode":"5","masterCode":"4201000","code":"4201023","name":"MONTERICO"},{"categoryCode":"5","masterCode":"4201000","code":"4201024","name":"NABUNA"},{"categoryCode":"5","masterCode":"4201000","code":"4201025","name":"PALAYAN"},{"categoryCode":"5","masterCode":"4201000","code":"4201026","name":"PELONG"},{"categoryCode":"5","masterCode":"4201000","code":"4201027","name":"OSPITAL "},{"categoryCode":"5","masterCode":"4201000","code":"4201028","name":"ROXAS"},{"categoryCode":"5","masterCode":"4201000","code":"4201029","name":"SAN PEDRO"},{"categoryCode":"5","masterCode":"4201000","code":"4201030","name":"SANTA ANA"},{"categoryCode":"5","masterCode":"4201000","code":"4201031","name":"SINAMPONGAN"},{"categoryCode":"5","masterCode":"4201000","code":"4201032","name":"TAGUANAO"},{"categoryCode":"5","masterCode":"4201000","code":"4201033","name":"TAWI-TAWI"},{"categoryCode":"5","masterCode":"4201000","code":"4201034","name":"TORIL"},{"categoryCode":"5","masterCode":"4201000","code":"4201035","name":"TUBURAN"},{"categoryCode":"5","masterCode":"4201000","code":"4201036","name":"ZAMORA"},{"categoryCode":"5","masterCode":"4201000","code":"4201037","name":"MACUBON"},{"categoryCode":"5","masterCode":"4201000","code":"4201038","name":"TUGAYA"}]}