{"regions":[{"categoryCode":"5","masterCode":"3710000","code":"3710001","name":"ABUYOGON"},{"categoryCode":"5","masterCode":"3710000","code":"3710002","name":"ANONANG"},{"categoryCode":"5","masterCode":"3710000","code":"3710003","name":"ARADO"},{"categoryCode":"5","masterCode":"3710000","code":"3710004","name":"BALAO"},{"categoryCode":"5","masterCode":"3710000","code":"3710005","name":"BALATSON"},{"categoryCode":"5","masterCode":"3710000","code":"3710006","name":"BALORINAY"},{"categoryCode":"5","masterCode":"3710000","code":"3710007","name":"BOBON"},{"categoryCode":"5","masterCode":"3710000","code":"3710008","name":"BUENAVISTA"},{"categoryCode":"5","masterCode":"3710000","code":"3710009","name":"BURI"},{"categoryCode":"5","masterCode":"3710000","code":"3710010","name":"CAANISLAGAN"},{"categoryCode":"5","masterCode":"3710000","code":"3710011","name":"CADAHUNAN"},{"categoryCode":"5","masterCode":"3710000","code":"3710012","name":"CAGANGON"},{"categoryCode":"5","masterCode":"3710000","code":"3710013","name":"CALI"},{"categoryCode":"5","masterCode":"3710000","code":"3710014","name":"CALSADAHAY"},{"categoryCode":"5","masterCode":"3710000","code":"3710015","name":"CANDAG-ON"},{"categoryCode":"5","masterCode":"3710000","code":"3710016","name":"CANSIBOY"},{"categoryCode":"5","masterCode":"3710000","code":"3710017","name":"CATAGBACAN"},{"categoryCode":"5","masterCode":"3710000","code":"3710018","name":"POBLACION DISTRICT I"},{"categoryCode":"5","masterCode":"3710000","code":"3710019","name":"POBLACION DISTRICT II"},{"categoryCode":"5","masterCode":"3710000","code":"3710020","name":"POBLACION DISTRICT III"},{"categoryCode":"5","masterCode":"3710000","code":"3710021","name":"POBLACION DISTRICT IV"},{"categoryCode":"5","masterCode":"3710000","code":"3710022","name":"POBLACION DISTRICT V"},{"categoryCode":"5","masterCode":"3710000","code":"3710023","name":"POBLACION DISTRICT VI"},{"categoryCode":"5","masterCode":"3710000","code":"3710024","name":"POBLACION DISTRICT VII"},{"categoryCode":"5","masterCode":"3710000","code":"3710025","name":"POBLACION DISTRICT VIII"},{"categoryCode":"5","masterCode":"3710000","code":"3710026","name":"POBLACION DISTRICT IX"},{"categoryCode":"5","masterCode":"3710000","code":"3710027","name":"DUMALAG"},{"categoryCode":"5","masterCode":"3710000","code":"3710028","name":"ILIHAN"},{"categoryCode":"5","masterCode":"3710000","code":"3710029","name":"ESPERANZA"},{"categoryCode":"5","masterCode":"3710000","code":"3710030","name":"GITABLA"},{"categoryCode":"5","masterCode":"3710000","code":"3710031","name":"HAPUNAN"},{"categoryCode":"5","masterCode":"3710000","code":"3710032","name":"HIBUNAWAN"},{"categoryCode":"5","masterCode":"3710000","code":"3710033","name":"HUGPA EAST"},{"categoryCode":"5","masterCode":"3710000","code":"3710034","name":"HUGPA WEST"},{"categoryCode":"5","masterCode":"3710000","code":"3710035","name":"KALAO"},{"categoryCode":"5","masterCode":"3710000","code":"3710036","name":"KAPARASANAN"},{"categoryCode":"5","masterCode":"3710000","code":"3710037","name":"LAGUIWAN"},{"categoryCode":"5","masterCode":"3710000","code":"3710038","name":"LIBAS"},{"categoryCode":"5","masterCode":"3710000","code":"3710039","name":"LIMBURAN"},{"categoryCode":"5","masterCode":"3710000","code":"3710040","name":"LOGSONGAN"},{"categoryCode":"5","masterCode":"3710000","code":"3710041","name":"MAABAB"},{"categoryCode":"5","masterCode":"3710000","code":"3710042","name":"MAGHUBAS"},{"categoryCode":"5","masterCode":"3710000","code":"3710043","name":"MAHAGNAO"},{"categoryCode":"5","masterCode":"3710000","code":"3710044","name":"MALABCA"},{"categoryCode":"5","masterCode":"3710000","code":"3710045","name":"MALAGUINABOT"},{"categoryCode":"5","masterCode":"3710000","code":"3710046","name":"MALAIHAO"},{"categoryCode":"5","masterCode":"3710000","code":"3710047","name":"MATIN-AO"},{"categoryCode":"5","masterCode":"3710000","code":"3710048","name":"MOGUING"},{"categoryCode":"5","masterCode":"3710000","code":"3710049","name":"PAGHUDLAN"},{"categoryCode":"5","masterCode":"3710000","code":"3710050","name":"PAITAN"},{"categoryCode":"5","masterCode":"3710000","code":"3710051","name":"PANGDAN"},{"categoryCode":"5","masterCode":"3710000","code":"3710052","name":"PATAG"},{"categoryCode":"5","masterCode":"3710000","code":"3710053","name":"PATONG"},{"categoryCode":"5","masterCode":"3710000","code":"3710054","name":"PAWA"},{"categoryCode":"5","masterCode":"3710000","code":"3710056","name":"ROXAS"},{"categoryCode":"5","masterCode":"3710000","code":"3710057","name":"SAMBEL"},{"categoryCode":"5","masterCode":"3710000","code":"3710058","name":"SAN ESTEBAN"},{"categoryCode":"5","masterCode":"3710000","code":"3710059","name":"SAN FERNANDO"},{"categoryCode":"5","masterCode":"3710000","code":"3710061","name":"SAN JOSE EAST"},{"categoryCode":"5","masterCode":"3710000","code":"3710062","name":"SAN JOSE WEST"},{"categoryCode":"5","masterCode":"3710000","code":"3710063","name":"SAN PABLO"},{"categoryCode":"5","masterCode":"3710000","code":"3710064","name":"TABUANON"},{"categoryCode":"5","masterCode":"3710000","code":"3710065","name":"TAGADTARAN"},{"categoryCode":"5","masterCode":"3710000","code":"3710066","name":"TAGHUYAN"},{"categoryCode":"5","masterCode":"3710000","code":"3710067","name":"TAKIN"},{"categoryCode":"5","masterCode":"3710000","code":"3710068","name":"TAMBIS"},{"categoryCode":"5","masterCode":"3710000","code":"3710070","name":"TOLOYAO"},{"categoryCode":"5","masterCode":"3710000","code":"3710071","name":"VILLA AURORA"},{"categoryCode":"5","masterCode":"3710000","code":"3710072","name":"VILLA CORAZON"},{"categoryCode":"5","masterCode":"3710000","code":"3710073","name":"VILLA PATRIA"},{"categoryCode":"5","masterCode":"3710000","code":"3710074","name":"VILLA ROSAS"},{"categoryCode":"5","masterCode":"3710000","code":"3710075","name":"KAGBANA"},{"categoryCode":"5","masterCode":"3710000","code":"3710076","name":"DAMULO-AN"},{"categoryCode":"5","masterCode":"3710000","code":"3710077","name":"DINA-AYAN"},{"categoryCode":"5","masterCode":"3710000","code":"3710078","name":"GAMAY"},{"categoryCode":"5","masterCode":"3710000","code":"3710079","name":"KALIPAYAN"},{"categoryCode":"5","masterCode":"3710000","code":"3710080","name":"TAMBUKO"}]}