{"regions":[{"categoryCode":null,"masterCode":null,"code":"58010057","name":"58010057"},{"categoryCode":null,"masterCode":null,"code":"58010058","name":"58010058"},{"categoryCode":null,"masterCode":null,"code":"58010059","name":"58010059"},{"categoryCode":null,"masterCode":null,"code":"58010060","name":"58010060"},{"categoryCode":null,"masterCode":null,"code":"58010061","name":"58010061"},{"categoryCode":null,"masterCode":null,"code":"58010062","name":"58010062"},{"categoryCode":null,"masterCode":null,"code":"58010063","name":"58010063"},{"categoryCode":null,"masterCode":null,"code":"58010064","name":"58010064"},{"categoryCode":null,"masterCode":null,"code":"58010065","name":"58010065"},{"categoryCode":null,"masterCode":null,"code":"58010066","name":"58010066"},{"categoryCode":null,"masterCode":null,"code":"58010067","name":"58010067"}]}