{"regions":[{"categoryCode":null,"masterCode":null,"code":"22170642","name":"22170642"},{"categoryCode":null,"masterCode":null,"code":"22170643","name":"22170643"},{"categoryCode":null,"masterCode":null,"code":"22170644","name":"22170644"},{"categoryCode":null,"masterCode":null,"code":"22170645","name":"22170645"},{"categoryCode":null,"masterCode":null,"code":"22170646","name":"22170646"},{"categoryCode":null,"masterCode":null,"code":"22170647","name":"22170647"},{"categoryCode":null,"masterCode":null,"code":"22170648","name":"22170648"},{"categoryCode":null,"masterCode":null,"code":"22170649","name":"22170649"},{"categoryCode":null,"masterCode":null,"code":"22170650","name":"22170650"},{"categoryCode":null,"masterCode":null,"code":"22170651","name":"22170651"},{"categoryCode":null,"masterCode":null,"code":"22170652","name":"22170652"},{"categoryCode":null,"masterCode":null,"code":"22170653","name":"22170653"},{"categoryCode":null,"masterCode":null,"code":"22170654","name":"22170654"},{"categoryCode":null,"masterCode":null,"code":"22170655","name":"22170655"},{"categoryCode":null,"masterCode":null,"code":"22170656","name":"22170656"},{"categoryCode":null,"masterCode":null,"code":"22170657","name":"22170657"}]}