{"regions":[{"categoryCode":"5","masterCode":"5506000","code":"5506002","name":"ARISTON ESTE"},{"categoryCode":"5","masterCode":"5506000","code":"5506003","name":"ARISTON WESTE"},{"categoryCode":"5","masterCode":"5506000","code":"5506004","name":"BANTOG"},{"categoryCode":"5","masterCode":"5506000","code":"5506005","name":"BARO"},{"categoryCode":"5","masterCode":"5506000","code":"5506006","name":"BOBONAN"},{"categoryCode":"5","masterCode":"5506000","code":"5506007","name":"CABALITIAN"},{"categoryCode":"5","masterCode":"5506000","code":"5506008","name":"CALEPAAN"},{"categoryCode":"5","masterCode":"5506000","code":"5506009","name":"CAROSUCAN NORTE"},{"categoryCode":"5","masterCode":"5506000","code":"5506010","name":"CAROSUCAN SUR"},{"categoryCode":"5","masterCode":"5506000","code":"5506011","name":"COLDIT"},{"categoryCode":"5","masterCode":"5506000","code":"5506012","name":"DOMANPOT"},{"categoryCode":"5","masterCode":"5506000","code":"5506013","name":"DUPAC"},{"categoryCode":"5","masterCode":"5506000","code":"5506014","name":"MACALONG"},{"categoryCode":"5","masterCode":"5506000","code":"5506015","name":"PALARIS"},{"categoryCode":"5","masterCode":"5506000","code":"5506016","name":"POBLACION EAST"},{"categoryCode":"5","masterCode":"5506000","code":"5506017","name":"POBLACION WEST"},{"categoryCode":"5","masterCode":"5506000","code":"5506018","name":"SAN VICENTE ESTE"},{"categoryCode":"5","masterCode":"5506000","code":"5506019","name":"SAN VICENTE WESTE"},{"categoryCode":"5","masterCode":"5506000","code":"5506020","name":"SANCHEZ"},{"categoryCode":"5","masterCode":"5506000","code":"5506021","name":"SOBOL"},{"categoryCode":"5","masterCode":"5506000","code":"5506022","name":"TOBOY"}]}