{"regions":[{"categoryCode":null,"masterCode":null,"code":"21170054","name":"21170054"},{"categoryCode":null,"masterCode":null,"code":"21170055","name":"21170055"},{"categoryCode":null,"masterCode":null,"code":"21170056","name":"21170056"},{"categoryCode":null,"masterCode":null,"code":"21170057","name":"21170057"},{"categoryCode":null,"masterCode":null,"code":"21170058","name":"21170058"},{"categoryCode":null,"masterCode":null,"code":"21170059","name":"21170059"},{"categoryCode":null,"masterCode":null,"code":"21170060","name":"21170060"},{"categoryCode":null,"masterCode":null,"code":"21170061","name":"21170061"},{"categoryCode":null,"masterCode":null,"code":"21170062","name":"21170062"},{"categoryCode":null,"masterCode":null,"code":"21170063","name":"21170063"},{"categoryCode":null,"masterCode":null,"code":"21170064","name":"21170064"}]}