{"regions":[{"categoryCode":"5","masterCode":"4520000","code":"4520001","name":"ABO-ABO"},{"categoryCode":"5","masterCode":"4520000","code":"4520002","name":"ALEGRIA"},{"categoryCode":"5","masterCode":"4520000","code":"4520003","name":"AMAYCO"},{"categoryCode":"5","masterCode":"4520000","code":"4520004","name":"ZONE I "},{"categoryCode":"5","masterCode":"4520000","code":"4520005","name":"ZONE II "},{"categoryCode":"5","masterCode":"4520000","code":"4520006","name":"ZONE III "},{"categoryCode":"5","masterCode":"4520000","code":"4520007","name":"ZONE IV "},{"categoryCode":"5","masterCode":"4520000","code":"4520008","name":"ZONE V "},{"categoryCode":"5","masterCode":"4520000","code":"4520009","name":"BLUMENTRITT"},{"categoryCode":"5","masterCode":"4520000","code":"4520010","name":"BUENAVISTA"},{"categoryCode":"5","masterCode":"4520000","code":"4520011","name":"CALIBAN"},{"categoryCode":"5","masterCode":"4520000","code":"4520012","name":"CANLANDOG"},{"categoryCode":"5","masterCode":"4520000","code":"4520013","name":"CANSILAYAN"},{"categoryCode":"5","masterCode":"4520000","code":"4520014","name":"DAMSITE"},{"categoryCode":"5","masterCode":"4520000","code":"4520015","name":"IGLAU-AN"},{"categoryCode":"5","masterCode":"4520000","code":"4520018","name":"LOPEZ JAENA"},{"categoryCode":"5","masterCode":"4520000","code":"4520019","name":"MINOYAN"},{"categoryCode":"5","masterCode":"4520000","code":"4520020","name":"PANDANON"},{"categoryCode":"5","masterCode":"4520000","code":"4520021","name":"SAN MIGUEL"},{"categoryCode":"5","masterCode":"4520000","code":"4520022","name":"SANTA CRUZ "},{"categoryCode":"5","masterCode":"4520000","code":"4520023","name":"SANTA ROSA"},{"categoryCode":"5","masterCode":"4520000","code":"4520024","name":"SALVACION"},{"categoryCode":"5","masterCode":"4520000","code":"4520025","name":"TALOTOG"}]}