{"regions":[{"categoryCode":"5","masterCode":"3901000","code":"3901001","name":"BARANGAY 1"},{"categoryCode":"5","masterCode":"3901000","code":"3901002","name":"BARANGAY 2"},{"categoryCode":"5","masterCode":"3901000","code":"3901003","name":"BARANGAY 3"},{"categoryCode":"5","masterCode":"3901000","code":"3901004","name":"BARANGAY 4"},{"categoryCode":"5","masterCode":"3901000","code":"3901005","name":"BARANGAY 5"},{"categoryCode":"5","masterCode":"3901000","code":"3901006","name":"BARANGAY 6"},{"categoryCode":"5","masterCode":"3901000","code":"3901007","name":"BARANGAY 7"},{"categoryCode":"5","masterCode":"3901000","code":"3901008","name":"BARANGAY 8"},{"categoryCode":"5","masterCode":"3901000","code":"3901009","name":"BARANGAY 9"},{"categoryCode":"5","masterCode":"3901000","code":"3901011","name":"BARANGAY 11"},{"categoryCode":"5","masterCode":"3901000","code":"3901012","name":"BARANGAY 12"},{"categoryCode":"5","masterCode":"3901000","code":"3901013","name":"BARANGAY 13"},{"categoryCode":"5","masterCode":"3901000","code":"3901014","name":"BARANGAY 14"},{"categoryCode":"5","masterCode":"3901000","code":"3901015","name":"BARANGAY 15"},{"categoryCode":"5","masterCode":"3901000","code":"3901016","name":"BARANGAY 16"},{"categoryCode":"5","masterCode":"3901000","code":"3901017","name":"BARANGAY 17"},{"categoryCode":"5","masterCode":"3901000","code":"3901018","name":"BARANGAY 18"},{"categoryCode":"5","masterCode":"3901000","code":"3901019","name":"BARANGAY 19"},{"categoryCode":"5","masterCode":"3901000","code":"3901020","name":"BARANGAY 20"},{"categoryCode":"5","masterCode":"3901000","code":"3901025","name":"BARANGAY 25"},{"categoryCode":"5","masterCode":"3901000","code":"3901026","name":"BARANGAY 26"},{"categoryCode":"5","masterCode":"3901000","code":"3901028","name":"BARANGAY 28"},{"categoryCode":"5","masterCode":"3901000","code":"3901029","name":"BARANGAY 29"},{"categoryCode":"5","masterCode":"3901000","code":"3901030","name":"BARANGAY 30"},{"categoryCode":"5","masterCode":"3901000","code":"3901031","name":"BARANGAY 31"},{"categoryCode":"5","masterCode":"3901000","code":"3901032","name":"BARANGAY 32"},{"categoryCode":"5","masterCode":"3901000","code":"3901033","name":"BARANGAY 33"},{"categoryCode":"5","masterCode":"3901000","code":"3901034","name":"BARANGAY 34"},{"categoryCode":"5","masterCode":"3901000","code":"3901035","name":"BARANGAY 35"},{"categoryCode":"5","masterCode":"3901000","code":"3901036","name":"BARANGAY 36"},{"categoryCode":"5","masterCode":"3901000","code":"3901037","name":"BARANGAY 37"},{"categoryCode":"5","masterCode":"3901000","code":"3901038","name":"BARANGAY 38"},{"categoryCode":"5","masterCode":"3901000","code":"3901039","name":"BARANGAY 39"},{"categoryCode":"5","masterCode":"3901000","code":"3901041","name":"BARANGAY 41"},{"categoryCode":"5","masterCode":"3901000","code":"3901042","name":"BARANGAY 42"},{"categoryCode":"5","masterCode":"3901000","code":"3901043","name":"BARANGAY 43"},{"categoryCode":"5","masterCode":"3901000","code":"3901044","name":"BARANGAY 44"},{"categoryCode":"5","masterCode":"3901000","code":"3901045","name":"BARANGAY 45"},{"categoryCode":"5","masterCode":"3901000","code":"3901046","name":"BARANGAY 46"},{"categoryCode":"5","masterCode":"3901000","code":"3901047","name":"BARANGAY 47"},{"categoryCode":"5","masterCode":"3901000","code":"3901048","name":"BARANGAY 48"},{"categoryCode":"5","masterCode":"3901000","code":"3901049","name":"BARANGAY 49"},{"categoryCode":"5","masterCode":"3901000","code":"3901050","name":"BARANGAY 50"},{"categoryCode":"5","masterCode":"3901000","code":"3901051","name":"BARANGAY 51"},{"categoryCode":"5","masterCode":"3901000","code":"3901052","name":"BARANGAY 52"},{"categoryCode":"5","masterCode":"3901000","code":"3901053","name":"BARANGAY 53"},{"categoryCode":"5","masterCode":"3901000","code":"3901054","name":"BARANGAY 54"},{"categoryCode":"5","masterCode":"3901000","code":"3901055","name":"BARANGAY 55"},{"categoryCode":"5","masterCode":"3901000","code":"3901056","name":"BARANGAY 56"},{"categoryCode":"5","masterCode":"3901000","code":"3901057","name":"BARANGAY 57"},{"categoryCode":"5","masterCode":"3901000","code":"3901058","name":"BARANGAY 58"},{"categoryCode":"5","masterCode":"3901000","code":"3901059","name":"BARANGAY 59"},{"categoryCode":"5","masterCode":"3901000","code":"3901060","name":"BARANGAY 60"},{"categoryCode":"5","masterCode":"3901000","code":"3901061","name":"BARANGAY 61"},{"categoryCode":"5","masterCode":"3901000","code":"3901062","name":"BARANGAY 62"},{"categoryCode":"5","masterCode":"3901000","code":"3901063","name":"BARANGAY 63"},{"categoryCode":"5","masterCode":"3901000","code":"3901064","name":"BARANGAY 64"},{"categoryCode":"5","masterCode":"3901000","code":"3901065","name":"BARANGAY 65"},{"categoryCode":"5","masterCode":"3901000","code":"3901066","name":"BARANGAY 66"},{"categoryCode":"5","masterCode":"3901000","code":"3901067","name":"BARANGAY 67"},{"categoryCode":"5","masterCode":"3901000","code":"3901068","name":"BARANGAY 68"},{"categoryCode":"5","masterCode":"3901000","code":"3901069","name":"BARANGAY 69"},{"categoryCode":"5","masterCode":"3901000","code":"3901070","name":"BARANGAY 70"},{"categoryCode":"5","masterCode":"3901000","code":"3901071","name":"BARANGAY 71"},{"categoryCode":"5","masterCode":"3901000","code":"3901072","name":"BARANGAY 72"},{"categoryCode":"5","masterCode":"3901000","code":"3901073","name":"BARANGAY 73"},{"categoryCode":"5","masterCode":"3901000","code":"3901074","name":"BARANGAY 74"},{"categoryCode":"5","masterCode":"3901000","code":"3901075","name":"BARANGAY 75"},{"categoryCode":"5","masterCode":"3901000","code":"3901076","name":"BARANGAY 76"},{"categoryCode":"5","masterCode":"3901000","code":"3901077","name":"BARANGAY 77"},{"categoryCode":"5","masterCode":"3901000","code":"3901078","name":"BARANGAY 78"},{"categoryCode":"5","masterCode":"3901000","code":"3901079","name":"BARANGAY 79"},{"categoryCode":"5","masterCode":"3901000","code":"3901080","name":"BARANGAY 80"},{"categoryCode":"5","masterCode":"3901000","code":"3901081","name":"BARANGAY 81"},{"categoryCode":"5","masterCode":"3901000","code":"3901082","name":"BARANGAY 82"},{"categoryCode":"5","masterCode":"3901000","code":"3901083","name":"BARANGAY 83"},{"categoryCode":"5","masterCode":"3901000","code":"3901084","name":"BARANGAY 84"},{"categoryCode":"5","masterCode":"3901000","code":"3901085","name":"BARANGAY 85"},{"categoryCode":"5","masterCode":"3901000","code":"3901086","name":"BARANGAY 86"},{"categoryCode":"5","masterCode":"3901000","code":"3901087","name":"BARANGAY 87"},{"categoryCode":"5","masterCode":"3901000","code":"3901088","name":"BARANGAY 88"},{"categoryCode":"5","masterCode":"3901000","code":"3901089","name":"BARANGAY 89"},{"categoryCode":"5","masterCode":"3901000","code":"3901090","name":"BARANGAY 90"},{"categoryCode":"5","masterCode":"3901000","code":"3901091","name":"BARANGAY 91"},{"categoryCode":"5","masterCode":"3901000","code":"3901092","name":"BARANGAY 92"},{"categoryCode":"5","masterCode":"3901000","code":"3901093","name":"BARANGAY 93"},{"categoryCode":"5","masterCode":"3901000","code":"3901094","name":"BARANGAY 94"},{"categoryCode":"5","masterCode":"3901000","code":"3901095","name":"BARANGAY 95"},{"categoryCode":"5","masterCode":"3901000","code":"3901096","name":"BARANGAY 96"},{"categoryCode":"5","masterCode":"3901000","code":"3901097","name":"BARANGAY 97"},{"categoryCode":"5","masterCode":"3901000","code":"3901098","name":"BARANGAY 98"},{"categoryCode":"5","masterCode":"3901000","code":"3901099","name":"BARANGAY 99"},{"categoryCode":"5","masterCode":"3901000","code":"3901100","name":"BARANGAY 100"},{"categoryCode":"5","masterCode":"3901000","code":"3901101","name":"BARANGAY 101"},{"categoryCode":"5","masterCode":"3901000","code":"3901102","name":"BARANGAY 102"},{"categoryCode":"5","masterCode":"3901000","code":"3901103","name":"BARANGAY 103"},{"categoryCode":"5","masterCode":"3901000","code":"3901104","name":"BARANGAY 104"},{"categoryCode":"5","masterCode":"3901000","code":"3901105","name":"BARANGAY 105"},{"categoryCode":"5","masterCode":"3901000","code":"3901106","name":"BARANGAY 106"},{"categoryCode":"5","masterCode":"3901000","code":"3901107","name":"BARANGAY 107"},{"categoryCode":"5","masterCode":"3901000","code":"3901108","name":"BARANGAY 108"},{"categoryCode":"5","masterCode":"3901000","code":"3901109","name":"BARANGAY 109"},{"categoryCode":"5","masterCode":"3901000","code":"3901110","name":"BARANGAY 110"},{"categoryCode":"5","masterCode":"3901000","code":"3901111","name":"BARANGAY 111"},{"categoryCode":"5","masterCode":"3901000","code":"3901112","name":"BARANGAY 112"},{"categoryCode":"5","masterCode":"3901000","code":"3901116","name":"BARANGAY 116"},{"categoryCode":"5","masterCode":"3901000","code":"3901117","name":"BARANGAY 117"},{"categoryCode":"5","masterCode":"3901000","code":"3901118","name":"BARANGAY 118"},{"categoryCode":"5","masterCode":"3901000","code":"3901119","name":"BARANGAY 119"},{"categoryCode":"5","masterCode":"3901000","code":"3901120","name":"BARANGAY 120"},{"categoryCode":"5","masterCode":"3901000","code":"3901121","name":"BARANGAY 121"},{"categoryCode":"5","masterCode":"3901000","code":"3901122","name":"BARANGAY 122"},{"categoryCode":"5","masterCode":"3901000","code":"3901123","name":"BARANGAY 123"},{"categoryCode":"5","masterCode":"3901000","code":"3901124","name":"BARANGAY 124"},{"categoryCode":"5","masterCode":"3901000","code":"3901125","name":"BARANGAY 125"},{"categoryCode":"5","masterCode":"3901000","code":"3901126","name":"BARANGAY 126"},{"categoryCode":"5","masterCode":"3901000","code":"3901127","name":"BARANGAY 127"},{"categoryCode":"5","masterCode":"3901000","code":"3901128","name":"BARANGAY 128"},{"categoryCode":"5","masterCode":"3901000","code":"3901129","name":"BARANGAY 129"},{"categoryCode":"5","masterCode":"3901000","code":"3901130","name":"BARANGAY 130"},{"categoryCode":"5","masterCode":"3901000","code":"3901131","name":"BARANGAY 131"},{"categoryCode":"5","masterCode":"3901000","code":"3901132","name":"BARANGAY 132"},{"categoryCode":"5","masterCode":"3901000","code":"3901133","name":"BARANGAY 133"},{"categoryCode":"5","masterCode":"3901000","code":"3901134","name":"BARANGAY 134"},{"categoryCode":"5","masterCode":"3901000","code":"3901135","name":"BARANGAY 135"},{"categoryCode":"5","masterCode":"3901000","code":"3901136","name":"BARANGAY 136"},{"categoryCode":"5","masterCode":"3901000","code":"3901137","name":"BARANGAY 137"},{"categoryCode":"5","masterCode":"3901000","code":"3901138","name":"BARANGAY 138"},{"categoryCode":"5","masterCode":"3901000","code":"3901139","name":"BARANGAY 139"},{"categoryCode":"5","masterCode":"3901000","code":"3901140","name":"BARANGAY 140"},{"categoryCode":"5","masterCode":"3901000","code":"3901141","name":"BARANGAY 141"},{"categoryCode":"5","masterCode":"3901000","code":"3901142","name":"BARANGAY 142"},{"categoryCode":"5","masterCode":"3901000","code":"3901143","name":"BARANGAY 143"},{"categoryCode":"5","masterCode":"3901000","code":"3901144","name":"BARANGAY 144"},{"categoryCode":"5","masterCode":"3901000","code":"3901145","name":"BARANGAY 145"},{"categoryCode":"5","masterCode":"3901000","code":"3901146","name":"BARANGAY 146"},{"categoryCode":"5","masterCode":"3901000","code":"3901147","name":"BARANGAY 147"},{"categoryCode":"5","masterCode":"3901000","code":"3901148","name":"BARANGAY 148"},{"categoryCode":"5","masterCode":"3901000","code":"3901149","name":"BARANGAY 149"},{"categoryCode":"5","masterCode":"3901000","code":"3901150","name":"BARANGAY 150"},{"categoryCode":"5","masterCode":"3901000","code":"3901151","name":"BARANGAY 151"},{"categoryCode":"5","masterCode":"3901000","code":"3901152","name":"BARANGAY 152"},{"categoryCode":"5","masterCode":"3901000","code":"3901153","name":"BARANGAY 153"},{"categoryCode":"5","masterCode":"3901000","code":"3901154","name":"BARANGAY 154"},{"categoryCode":"5","masterCode":"3901000","code":"3901155","name":"BARANGAY 155"},{"categoryCode":"5","masterCode":"3901000","code":"3901156","name":"BARANGAY 156"},{"categoryCode":"5","masterCode":"3901000","code":"3901157","name":"BARANGAY 157"},{"categoryCode":"5","masterCode":"3901000","code":"3901158","name":"BARANGAY 158"},{"categoryCode":"5","masterCode":"3901000","code":"3901159","name":"BARANGAY 159"},{"categoryCode":"5","masterCode":"3901000","code":"3901160","name":"BARANGAY 160"},{"categoryCode":"5","masterCode":"3901000","code":"3901161","name":"BARANGAY 161"},{"categoryCode":"5","masterCode":"3901000","code":"3901162","name":"BARANGAY 162"},{"categoryCode":"5","masterCode":"3901000","code":"3901163","name":"BARANGAY 163"},{"categoryCode":"5","masterCode":"3901000","code":"3901164","name":"BARANGAY 164"},{"categoryCode":"5","masterCode":"3901000","code":"3901165","name":"BARANGAY 165"},{"categoryCode":"5","masterCode":"3901000","code":"3901166","name":"BARANGAY 166"},{"categoryCode":"5","masterCode":"3901000","code":"3901167","name":"BARANGAY 167"},{"categoryCode":"5","masterCode":"3901000","code":"3901168","name":"BARANGAY 168"},{"categoryCode":"5","masterCode":"3901000","code":"3901169","name":"BARANGAY 169"},{"categoryCode":"5","masterCode":"3901000","code":"3901170","name":"BARANGAY 170"},{"categoryCode":"5","masterCode":"3901000","code":"3901171","name":"BARANGAY 171"},{"categoryCode":"5","masterCode":"3901000","code":"3901172","name":"BARANGAY 172"},{"categoryCode":"5","masterCode":"3901000","code":"3901173","name":"BARANGAY 173"},{"categoryCode":"5","masterCode":"3901000","code":"3901174","name":"BARANGAY 174"},{"categoryCode":"5","masterCode":"3901000","code":"3901175","name":"BARANGAY 175"},{"categoryCode":"5","masterCode":"3901000","code":"3901176","name":"BARANGAY 176"},{"categoryCode":"5","masterCode":"3901000","code":"3901177","name":"BARANGAY 177"},{"categoryCode":"5","masterCode":"3901000","code":"3901178","name":"BARANGAY 178"},{"categoryCode":"5","masterCode":"3901000","code":"3901179","name":"BARANGAY 179"},{"categoryCode":"5","masterCode":"3901000","code":"3901180","name":"BARANGAY 180"},{"categoryCode":"5","masterCode":"3901000","code":"3901181","name":"BARANGAY 181"},{"categoryCode":"5","masterCode":"3901000","code":"3901182","name":"BARANGAY 182"},{"categoryCode":"5","masterCode":"3901000","code":"3901183","name":"BARANGAY 183"},{"categoryCode":"5","masterCode":"3901000","code":"3901184","name":"BARANGAY 184"},{"categoryCode":"5","masterCode":"3901000","code":"3901185","name":"BARANGAY 185"},{"categoryCode":"5","masterCode":"3901000","code":"3901186","name":"BARANGAY 186"},{"categoryCode":"5","masterCode":"3901000","code":"3901187","name":"BARANGAY 187"},{"categoryCode":"5","masterCode":"3901000","code":"3901188","name":"BARANGAY 188"},{"categoryCode":"5","masterCode":"3901000","code":"3901189","name":"BARANGAY 189"},{"categoryCode":"5","masterCode":"3901000","code":"3901190","name":"BARANGAY 190"},{"categoryCode":"5","masterCode":"3901000","code":"3901191","name":"BARANGAY 191"},{"categoryCode":"5","masterCode":"3901000","code":"3901192","name":"BARANGAY 192"},{"categoryCode":"5","masterCode":"3901000","code":"3901193","name":"BARANGAY 193"},{"categoryCode":"5","masterCode":"3901000","code":"3901194","name":"BARANGAY 194"},{"categoryCode":"5","masterCode":"3901000","code":"3901195","name":"BARANGAY 195"},{"categoryCode":"5","masterCode":"3901000","code":"3901196","name":"BARANGAY 196"},{"categoryCode":"5","masterCode":"3901000","code":"3901197","name":"BARANGAY 197"},{"categoryCode":"5","masterCode":"3901000","code":"3901198","name":"BARANGAY 198"},{"categoryCode":"5","masterCode":"3901000","code":"3901199","name":"BARANGAY 199"},{"categoryCode":"5","masterCode":"3901000","code":"3901200","name":"BARANGAY 200"},{"categoryCode":"5","masterCode":"3901000","code":"3901201","name":"BARANGAY 201"},{"categoryCode":"5","masterCode":"3901000","code":"3901202","name":"BARANGAY 202"},{"categoryCode":"5","masterCode":"3901000","code":"3901203","name":"BARANGAY 202-A"},{"categoryCode":"5","masterCode":"3901000","code":"3901204","name":"BARANGAY 203"},{"categoryCode":"5","masterCode":"3901000","code":"3901205","name":"BARANGAY 204"},{"categoryCode":"5","masterCode":"3901000","code":"3901206","name":"BARANGAY 205"},{"categoryCode":"5","masterCode":"3901000","code":"3901207","name":"BARANGAY 206"},{"categoryCode":"5","masterCode":"3901000","code":"3901208","name":"BARANGAY 207"},{"categoryCode":"5","masterCode":"3901000","code":"3901209","name":"BARANGAY 208"},{"categoryCode":"5","masterCode":"3901000","code":"3901210","name":"BARANGAY 209"},{"categoryCode":"5","masterCode":"3901000","code":"3901211","name":"BARANGAY 210"},{"categoryCode":"5","masterCode":"3901000","code":"3901212","name":"BARANGAY 211"},{"categoryCode":"5","masterCode":"3901000","code":"3901213","name":"BARANGAY 212"},{"categoryCode":"5","masterCode":"3901000","code":"3901214","name":"BARANGAY 213"},{"categoryCode":"5","masterCode":"3901000","code":"3901215","name":"BARANGAY 214"},{"categoryCode":"5","masterCode":"3901000","code":"3901216","name":"BARANGAY 215"},{"categoryCode":"5","masterCode":"3901000","code":"3901217","name":"BARANGAY 216"},{"categoryCode":"5","masterCode":"3901000","code":"3901218","name":"BARANGAY 217"},{"categoryCode":"5","masterCode":"3901000","code":"3901219","name":"BARANGAY 218"},{"categoryCode":"5","masterCode":"3901000","code":"3901220","name":"BARANGAY 219"},{"categoryCode":"5","masterCode":"3901000","code":"3901221","name":"BARANGAY 220"},{"categoryCode":"5","masterCode":"3901000","code":"3901222","name":"BARANGAY 221"},{"categoryCode":"5","masterCode":"3901000","code":"3901223","name":"BARANGAY 222"},{"categoryCode":"5","masterCode":"3901000","code":"3901224","name":"BARANGAY 223"},{"categoryCode":"5","masterCode":"3901000","code":"3901225","name":"BARANGAY 224"},{"categoryCode":"5","masterCode":"3901000","code":"3901226","name":"BARANGAY 225"},{"categoryCode":"5","masterCode":"3901000","code":"3901227","name":"BARANGAY 226"},{"categoryCode":"5","masterCode":"3901000","code":"3901228","name":"BARANGAY 227"},{"categoryCode":"5","masterCode":"3901000","code":"3901229","name":"BARANGAY 228"},{"categoryCode":"5","masterCode":"3901000","code":"3901230","name":"BARANGAY 229"},{"categoryCode":"5","masterCode":"3901000","code":"3901231","name":"BARANGAY 230"},{"categoryCode":"5","masterCode":"3901000","code":"3901232","name":"BARANGAY 231"},{"categoryCode":"5","masterCode":"3901000","code":"3901233","name":"BARANGAY 232"},{"categoryCode":"5","masterCode":"3901000","code":"3901234","name":"BARANGAY 233"},{"categoryCode":"5","masterCode":"3901000","code":"3901235","name":"BARANGAY 234"},{"categoryCode":"5","masterCode":"3901000","code":"3901236","name":"BARANGAY 235"},{"categoryCode":"5","masterCode":"3901000","code":"3901237","name":"BARANGAY 236"},{"categoryCode":"5","masterCode":"3901000","code":"3901238","name":"BARANGAY 237"},{"categoryCode":"5","masterCode":"3901000","code":"3901239","name":"BARANGAY 238"},{"categoryCode":"5","masterCode":"3901000","code":"3901240","name":"BARANGAY 239"},{"categoryCode":"5","masterCode":"3901000","code":"3901241","name":"BARANGAY 240"},{"categoryCode":"5","masterCode":"3901000","code":"3901242","name":"BARANGAY 241"},{"categoryCode":"5","masterCode":"3901000","code":"3901243","name":"BARANGAY 242"},{"categoryCode":"5","masterCode":"3901000","code":"3901244","name":"BARANGAY 243"},{"categoryCode":"5","masterCode":"3901000","code":"3901245","name":"BARANGAY 244"},{"categoryCode":"5","masterCode":"3901000","code":"3901246","name":"BARANGAY 245"},{"categoryCode":"5","masterCode":"3901000","code":"3901247","name":"BARANGAY 246"},{"categoryCode":"5","masterCode":"3901000","code":"3901248","name":"BARANGAY 247"},{"categoryCode":"5","masterCode":"3901000","code":"3901249","name":"BARANGAY 248"},{"categoryCode":"5","masterCode":"3901000","code":"3901250","name":"BARANGAY 249"},{"categoryCode":"5","masterCode":"3901000","code":"3901251","name":"BARANGAY 250"},{"categoryCode":"5","masterCode":"3901000","code":"3901252","name":"BARANGAY 251"},{"categoryCode":"5","masterCode":"3901000","code":"3901253","name":"BARANGAY 252"},{"categoryCode":"5","masterCode":"3901000","code":"3901254","name":"BARANGAY 253"},{"categoryCode":"5","masterCode":"3901000","code":"3901255","name":"BARANGAY 254"},{"categoryCode":"5","masterCode":"3901000","code":"3901256","name":"BARANGAY 255"},{"categoryCode":"5","masterCode":"3901000","code":"3901257","name":"BARANGAY 256"},{"categoryCode":"5","masterCode":"3901000","code":"3901258","name":"BARANGAY 257"},{"categoryCode":"5","masterCode":"3901000","code":"3901259","name":"BARANGAY 258"},{"categoryCode":"5","masterCode":"3901000","code":"3901260","name":"BARANGAY 259"},{"categoryCode":"5","masterCode":"3901000","code":"3901261","name":"BARANGAY 260"},{"categoryCode":"5","masterCode":"3901000","code":"3901262","name":"BARANGAY 261"},{"categoryCode":"5","masterCode":"3901000","code":"3901263","name":"BARANGAY 262"},{"categoryCode":"5","masterCode":"3901000","code":"3901264","name":"BARANGAY 263"},{"categoryCode":"5","masterCode":"3901000","code":"3901265","name":"BARANGAY 264"},{"categoryCode":"5","masterCode":"3901000","code":"3901266","name":"BARANGAY 265"},{"categoryCode":"5","masterCode":"3901000","code":"3901267","name":"BARANGAY 266"},{"categoryCode":"5","masterCode":"3901000","code":"3901268","name":"BARANGAY 267"},{"categoryCode":"5","masterCode":"3901000","code":"3902001","name":"BARANGAY 287"},{"categoryCode":"5","masterCode":"3901000","code":"3902002","name":"BARANGAY 288"},{"categoryCode":"5","masterCode":"3901000","code":"3902003","name":"BARANGAY 289"},{"categoryCode":"5","masterCode":"3901000","code":"3902004","name":"BARANGAY 290"},{"categoryCode":"5","masterCode":"3901000","code":"3902005","name":"BARANGAY 291"},{"categoryCode":"5","masterCode":"3901000","code":"3902006","name":"BARANGAY 292"},{"categoryCode":"5","masterCode":"3901000","code":"3902007","name":"BARANGAY 293"},{"categoryCode":"5","masterCode":"3901000","code":"3902008","name":"BARANGAY 294"},{"categoryCode":"5","masterCode":"3901000","code":"3902009","name":"BARANGAY 295"},{"categoryCode":"5","masterCode":"3901000","code":"3902010","name":"BARANGAY 296"},{"categoryCode":"5","masterCode":"3901000","code":"3903003","name":"BARANGAY 383"},{"categoryCode":"5","masterCode":"3901000","code":"3903004","name":"BARANGAY 384"},{"categoryCode":"5","masterCode":"3901000","code":"3903005","name":"BARANGAY 385"},{"categoryCode":"5","masterCode":"3901000","code":"3903006","name":"BARANGAY 386"},{"categoryCode":"5","masterCode":"3901000","code":"3903007","name":"BARANGAY 387"},{"categoryCode":"5","masterCode":"3901000","code":"3903008","name":"BARANGAY 388"},{"categoryCode":"5","masterCode":"3901000","code":"3903009","name":"BARANGAY 389"},{"categoryCode":"5","masterCode":"3901000","code":"3903010","name":"BARANGAY 390"},{"categoryCode":"5","masterCode":"3901000","code":"3903011","name":"BARANGAY 391"},{"categoryCode":"5","masterCode":"3901000","code":"3903012","name":"BARANGAY 392"},{"categoryCode":"5","masterCode":"3901000","code":"3903013","name":"BARANGAY 393"},{"categoryCode":"5","masterCode":"3901000","code":"3903014","name":"BARANGAY 394"},{"categoryCode":"5","masterCode":"3901000","code":"3903015","name":"BARANGAY 306"},{"categoryCode":"5","masterCode":"3901000","code":"3903016","name":"BARANGAY 307"},{"categoryCode":"5","masterCode":"3901000","code":"3903017","name":"BARANGAY 308"},{"categoryCode":"5","masterCode":"3901000","code":"3903018","name":"BARANGAY 309"},{"categoryCode":"5","masterCode":"3901000","code":"3904001","name":"BARANGAY 268"},{"categoryCode":"5","masterCode":"3901000","code":"3904002","name":"BARANGAY 269"},{"categoryCode":"5","masterCode":"3901000","code":"3904003","name":"BARANGAY 270"},{"categoryCode":"5","masterCode":"3901000","code":"3904004","name":"BARANGAY 271"},{"categoryCode":"5","masterCode":"3901000","code":"3904005","name":"BARANGAY 272"},{"categoryCode":"5","masterCode":"3901000","code":"3904006","name":"BARANGAY 273"},{"categoryCode":"5","masterCode":"3901000","code":"3904007","name":"BARANGAY 274"},{"categoryCode":"5","masterCode":"3901000","code":"3904008","name":"BARANGAY 275"},{"categoryCode":"5","masterCode":"3901000","code":"3904009","name":"BARANGAY 276"},{"categoryCode":"5","masterCode":"3901000","code":"3904014","name":"BARANGAY 281"},{"categoryCode":"5","masterCode":"3901000","code":"3904015","name":"BARANGAY 282"},{"categoryCode":"5","masterCode":"3901000","code":"3904016","name":"BARANGAY 283"},{"categoryCode":"5","masterCode":"3901000","code":"3904017","name":"BARANGAY 284"},{"categoryCode":"5","masterCode":"3901000","code":"3904018","name":"BARANGAY 285"},{"categoryCode":"5","masterCode":"3901000","code":"3904019","name":"BARANGAY 286"},{"categoryCode":"5","masterCode":"3901000","code":"3905001","name":"BARANGAY 297"},{"categoryCode":"5","masterCode":"3901000","code":"3905002","name":"BARANGAY 298"},{"categoryCode":"5","masterCode":"3901000","code":"3905003","name":"BARANGAY 299"},{"categoryCode":"5","masterCode":"3901000","code":"3905004","name":"BARANGAY 300"},{"categoryCode":"5","masterCode":"3901000","code":"3905005","name":"BARANGAY 301"},{"categoryCode":"5","masterCode":"3901000","code":"3905006","name":"BARANGAY 302"},{"categoryCode":"5","masterCode":"3901000","code":"3905007","name":"BARANGAY 303"},{"categoryCode":"5","masterCode":"3901000","code":"3905008","name":"BARANGAY 304"},{"categoryCode":"5","masterCode":"3901000","code":"3905009","name":"BARANGAY 305"},{"categoryCode":"5","masterCode":"3901000","code":"3905012","name":"BARANGAY 310"},{"categoryCode":"5","masterCode":"3901000","code":"3905013","name":"BARANGAY 311"},{"categoryCode":"5","masterCode":"3901000","code":"3905014","name":"BARANGAY 312"},{"categoryCode":"5","masterCode":"3901000","code":"3905015","name":"BARANGAY 313"},{"categoryCode":"5","masterCode":"3901000","code":"3905016","name":"BARANGAY 314"},{"categoryCode":"5","masterCode":"3901000","code":"3905017","name":"BARANGAY 315"},{"categoryCode":"5","masterCode":"3901000","code":"3905018","name":"BARANGAY 316"},{"categoryCode":"5","masterCode":"3901000","code":"3905019","name":"BARANGAY 317"},{"categoryCode":"5","masterCode":"3901000","code":"3905020","name":"BARANGAY 318"},{"categoryCode":"5","masterCode":"3901000","code":"3905021","name":"BARANGAY 319"},{"categoryCode":"5","masterCode":"3901000","code":"3905022","name":"BARANGAY 320"},{"categoryCode":"5","masterCode":"3901000","code":"3905023","name":"BARANGAY 321"},{"categoryCode":"5","masterCode":"3901000","code":"3905024","name":"BARANGAY 322"},{"categoryCode":"5","masterCode":"3901000","code":"3905025","name":"BARANGAY 323"},{"categoryCode":"5","masterCode":"3901000","code":"3905026","name":"BARANGAY 324"},{"categoryCode":"5","masterCode":"3901000","code":"3905027","name":"BARANGAY 325"},{"categoryCode":"5","masterCode":"3901000","code":"3905028","name":"BARANGAY 326"},{"categoryCode":"5","masterCode":"3901000","code":"3905029","name":"BARANGAY 327"},{"categoryCode":"5","masterCode":"3901000","code":"3905030","name":"BARANGAY 328"},{"categoryCode":"5","masterCode":"3901000","code":"3905031","name":"BARANGAY 329"},{"categoryCode":"5","masterCode":"3901000","code":"3905032","name":"BARANGAY 330"},{"categoryCode":"5","masterCode":"3901000","code":"3905033","name":"BARANGAY 331"},{"categoryCode":"5","masterCode":"3901000","code":"3905034","name":"BARANGAY 332"},{"categoryCode":"5","masterCode":"3901000","code":"3905035","name":"BARANGAY 333"},{"categoryCode":"5","masterCode":"3901000","code":"3905036","name":"BARANGAY 334"},{"categoryCode":"5","masterCode":"3901000","code":"3905037","name":"BARANGAY 335"},{"categoryCode":"5","masterCode":"3901000","code":"3905038","name":"BARANGAY 336"},{"categoryCode":"5","masterCode":"3901000","code":"3905039","name":"BARANGAY 337"},{"categoryCode":"5","masterCode":"3901000","code":"3905040","name":"BARANGAY 338"},{"categoryCode":"5","masterCode":"3901000","code":"3905041","name":"BARANGAY 339"},{"categoryCode":"5","masterCode":"3901000","code":"3905042","name":"BARANGAY 340"},{"categoryCode":"5","masterCode":"3901000","code":"3905043","name":"BARANGAY 341"},{"categoryCode":"5","masterCode":"3901000","code":"3905044","name":"BARANGAY 342"},{"categoryCode":"5","masterCode":"3901000","code":"3905045","name":"BARANGAY 343"},{"categoryCode":"5","masterCode":"3901000","code":"3905046","name":"BARANGAY 344"},{"categoryCode":"5","masterCode":"3901000","code":"3905047","name":"BARANGAY 345"},{"categoryCode":"5","masterCode":"3901000","code":"3905048","name":"BARANGAY 346"},{"categoryCode":"5","masterCode":"3901000","code":"3905049","name":"BARANGAY 347"},{"categoryCode":"5","masterCode":"3901000","code":"3905050","name":"BARANGAY 348"},{"categoryCode":"5","masterCode":"3901000","code":"3905051","name":"BARANGAY 349"},{"categoryCode":"5","masterCode":"3901000","code":"3905052","name":"BARANGAY 350"},{"categoryCode":"5","masterCode":"3901000","code":"3905053","name":"BARANGAY 351"},{"categoryCode":"5","masterCode":"3901000","code":"3905054","name":"BARANGAY 352"},{"categoryCode":"5","masterCode":"3901000","code":"3905055","name":"BARANGAY 353"},{"categoryCode":"5","masterCode":"3901000","code":"3905056","name":"BARANGAY 354"},{"categoryCode":"5","masterCode":"3901000","code":"3905057","name":"BARANGAY 355"},{"categoryCode":"5","masterCode":"3901000","code":"3905058","name":"BARANGAY 356"},{"categoryCode":"5","masterCode":"3901000","code":"3905059","name":"BARANGAY 357"},{"categoryCode":"5","masterCode":"3901000","code":"3905060","name":"BARANGAY 358"},{"categoryCode":"5","masterCode":"3901000","code":"3905061","name":"BARANGAY 359"},{"categoryCode":"5","masterCode":"3901000","code":"3905062","name":"BARANGAY 360"},{"categoryCode":"5","masterCode":"3901000","code":"3905063","name":"BARANGAY 361"},{"categoryCode":"5","masterCode":"3901000","code":"3905064","name":"BARANGAY 362"},{"categoryCode":"5","masterCode":"3901000","code":"3905065","name":"BARANGAY 363"},{"categoryCode":"5","masterCode":"3901000","code":"3905066","name":"BARANGAY 364"},{"categoryCode":"5","masterCode":"3901000","code":"3905067","name":"BARANGAY 365"},{"categoryCode":"5","masterCode":"3901000","code":"3905069","name":"BARANGAY 366"},{"categoryCode":"5","masterCode":"3901000","code":"3905070","name":"BARANGAY 367"},{"categoryCode":"5","masterCode":"3901000","code":"3905071","name":"BARANGAY 368"},{"categoryCode":"5","masterCode":"3901000","code":"3905072","name":"BARANGAY 369"},{"categoryCode":"5","masterCode":"3901000","code":"3905073","name":"BARANGAY 370"},{"categoryCode":"5","masterCode":"3901000","code":"3905074","name":"BARANGAY 371"},{"categoryCode":"5","masterCode":"3901000","code":"3905075","name":"BARANGAY 372"},{"categoryCode":"5","masterCode":"3901000","code":"3905076","name":"BARANGAY 373"},{"categoryCode":"5","masterCode":"3901000","code":"3905077","name":"BARANGAY 374"},{"categoryCode":"5","masterCode":"3901000","code":"3905078","name":"BARANGAY 375"},{"categoryCode":"5","masterCode":"3901000","code":"3905079","name":"BARANGAY 376"},{"categoryCode":"5","masterCode":"3901000","code":"3905080","name":"BARANGAY 377"},{"categoryCode":"5","masterCode":"3901000","code":"3905081","name":"BARANGAY 378"},{"categoryCode":"5","masterCode":"3901000","code":"3905082","name":"BARANGAY 379"},{"categoryCode":"5","masterCode":"3901000","code":"3905083","name":"BARANGAY 380"},{"categoryCode":"5","masterCode":"3901000","code":"3905084","name":"BARANGAY 381"},{"categoryCode":"5","masterCode":"3901000","code":"3905085","name":"BARANGAY 382"},{"categoryCode":"5","masterCode":"3901000","code":"3906001","name":"BARANGAY 395"},{"categoryCode":"5","masterCode":"3901000","code":"3906002","name":"BARANGAY 396"},{"categoryCode":"5","masterCode":"3901000","code":"3906003","name":"BARANGAY 397"},{"categoryCode":"5","masterCode":"3901000","code":"3906004","name":"BARANGAY 398"},{"categoryCode":"5","masterCode":"3901000","code":"3906005","name":"BARANGAY 399"},{"categoryCode":"5","masterCode":"3901000","code":"3906006","name":"BARANGAY 400"},{"categoryCode":"5","masterCode":"3901000","code":"3906007","name":"BARANGAY 401"},{"categoryCode":"5","masterCode":"3901000","code":"3906008","name":"BARANGAY 402"},{"categoryCode":"5","masterCode":"3901000","code":"3906009","name":"BARANGAY 403"},{"categoryCode":"5","masterCode":"3901000","code":"3906010","name":"BARANGAY 404"},{"categoryCode":"5","masterCode":"3901000","code":"3906011","name":"BARANGAY 405"},{"categoryCode":"5","masterCode":"3901000","code":"3906012","name":"BARANGAY 406"},{"categoryCode":"5","masterCode":"3901000","code":"3906013","name":"BARANGAY 407"},{"categoryCode":"5","masterCode":"3901000","code":"3906014","name":"BARANGAY 408"},{"categoryCode":"5","masterCode":"3901000","code":"3906015","name":"BARANGAY 409"},{"categoryCode":"5","masterCode":"3901000","code":"3906016","name":"BARANGAY 410"},{"categoryCode":"5","masterCode":"3901000","code":"3906017","name":"BARANGAY 411"},{"categoryCode":"5","masterCode":"3901000","code":"3906018","name":"BARANGAY 412"},{"categoryCode":"5","masterCode":"3901000","code":"3906019","name":"BARANGAY 413"},{"categoryCode":"5","masterCode":"3901000","code":"3906020","name":"BARANGAY 414"},{"categoryCode":"5","masterCode":"3901000","code":"3906021","name":"BARANGAY 415"},{"categoryCode":"5","masterCode":"3901000","code":"3906022","name":"BARANGAY 416"},{"categoryCode":"5","masterCode":"3901000","code":"3906023","name":"BARANGAY 417"},{"categoryCode":"5","masterCode":"3901000","code":"3906024","name":"BARANGAY 418"},{"categoryCode":"5","masterCode":"3901000","code":"3906025","name":"BARANGAY 419"},{"categoryCode":"5","masterCode":"3901000","code":"3906026","name":"BARANGAY 420"},{"categoryCode":"5","masterCode":"3901000","code":"3906027","name":"BARANGAY 421"},{"categoryCode":"5","masterCode":"3901000","code":"3906028","name":"BARANGAY 422"},{"categoryCode":"5","masterCode":"3901000","code":"3906029","name":"BARANGAY 423"},{"categoryCode":"5","masterCode":"3901000","code":"3906030","name":"BARANGAY 424"},{"categoryCode":"5","masterCode":"3901000","code":"3906031","name":"BARANGAY 425"},{"categoryCode":"5","masterCode":"3901000","code":"3906032","name":"BARANGAY 426"},{"categoryCode":"5","masterCode":"3901000","code":"3906033","name":"BARANGAY 427"},{"categoryCode":"5","masterCode":"3901000","code":"3906034","name":"BARANGAY 428"},{"categoryCode":"5","masterCode":"3901000","code":"3906035","name":"BARANGAY 429"},{"categoryCode":"5","masterCode":"3901000","code":"3906036","name":"BARANGAY 430"},{"categoryCode":"5","masterCode":"3901000","code":"3906037","name":"BARANGAY 431"},{"categoryCode":"5","masterCode":"3901000","code":"3906038","name":"BARANGAY 432"},{"categoryCode":"5","masterCode":"3901000","code":"3906039","name":"BARANGAY 433"},{"categoryCode":"5","masterCode":"3901000","code":"3906040","name":"BARANGAY 434"},{"categoryCode":"5","masterCode":"3901000","code":"3906041","name":"BARANGAY 435"},{"categoryCode":"5","masterCode":"3901000","code":"3906042","name":"BARANGAY 436"},{"categoryCode":"5","masterCode":"3901000","code":"3906043","name":"BARANGAY 437"},{"categoryCode":"5","masterCode":"3901000","code":"3906044","name":"BARANGAY 438"},{"categoryCode":"5","masterCode":"3901000","code":"3906045","name":"BARANGAY 439"},{"categoryCode":"5","masterCode":"3901000","code":"3906046","name":"BARANGAY 440"},{"categoryCode":"5","masterCode":"3901000","code":"3906047","name":"BARANGAY 441"},{"categoryCode":"5","masterCode":"3901000","code":"3906048","name":"BARANGAY 442"},{"categoryCode":"5","masterCode":"3901000","code":"3906049","name":"BARANGAY 443"},{"categoryCode":"5","masterCode":"3901000","code":"3906050","name":"BARANGAY 444"},{"categoryCode":"5","masterCode":"3901000","code":"3906051","name":"BARANGAY 445"},{"categoryCode":"5","masterCode":"3901000","code":"3906052","name":"BARANGAY 446"},{"categoryCode":"5","masterCode":"3901000","code":"3906053","name":"BARANGAY 447"},{"categoryCode":"5","masterCode":"3901000","code":"3906054","name":"BARANGAY 448"},{"categoryCode":"5","masterCode":"3901000","code":"3906055","name":"BARANGAY 449"},{"categoryCode":"5","masterCode":"3901000","code":"3906056","name":"BARANGAY 450"},{"categoryCode":"5","masterCode":"3901000","code":"3906057","name":"BARANGAY 451"},{"categoryCode":"5","masterCode":"3901000","code":"3906058","name":"BARANGAY 452"},{"categoryCode":"5","masterCode":"3901000","code":"3906059","name":"BARANGAY 453"},{"categoryCode":"5","masterCode":"3901000","code":"3906060","name":"BARANGAY 454"},{"categoryCode":"5","masterCode":"3901000","code":"3906061","name":"BARANGAY 455"},{"categoryCode":"5","masterCode":"3901000","code":"3906062","name":"BARANGAY 456"},{"categoryCode":"5","masterCode":"3901000","code":"3906063","name":"BARANGAY 457"},{"categoryCode":"5","masterCode":"3901000","code":"3906064","name":"BARANGAY 458"},{"categoryCode":"5","masterCode":"3901000","code":"3906065","name":"BARANGAY 459"},{"categoryCode":"5","masterCode":"3901000","code":"3906066","name":"BARANGAY 460"},{"categoryCode":"5","masterCode":"3901000","code":"3906067","name":"BARANGAY 461"},{"categoryCode":"5","masterCode":"3901000","code":"3906068","name":"BARANGAY 462"},{"categoryCode":"5","masterCode":"3901000","code":"3906069","name":"BARANGAY 463"},{"categoryCode":"5","masterCode":"3901000","code":"3906070","name":"BARANGAY 464"},{"categoryCode":"5","masterCode":"3901000","code":"3906071","name":"BARANGAY 465"},{"categoryCode":"5","masterCode":"3901000","code":"3906072","name":"BARANGAY 466"},{"categoryCode":"5","masterCode":"3901000","code":"3906073","name":"BARANGAY 467"},{"categoryCode":"5","masterCode":"3901000","code":"3906074","name":"BARANGAY 468"},{"categoryCode":"5","masterCode":"3901000","code":"3906075","name":"BARANGAY 469"},{"categoryCode":"5","masterCode":"3901000","code":"3906076","name":"BARANGAY 470"},{"categoryCode":"5","masterCode":"3901000","code":"3906077","name":"BARANGAY 471"},{"categoryCode":"5","masterCode":"3901000","code":"3906078","name":"BARANGAY 472"},{"categoryCode":"5","masterCode":"3901000","code":"3906079","name":"BARANGAY 473"},{"categoryCode":"5","masterCode":"3901000","code":"3906080","name":"BARANGAY 474"},{"categoryCode":"5","masterCode":"3901000","code":"3906081","name":"BARANGAY 475"},{"categoryCode":"5","masterCode":"3901000","code":"3906082","name":"BARANGAY 476"},{"categoryCode":"5","masterCode":"3901000","code":"3906083","name":"BARANGAY 477"},{"categoryCode":"5","masterCode":"3901000","code":"3906084","name":"BARANGAY 478"},{"categoryCode":"5","masterCode":"3901000","code":"3906085","name":"BARANGAY 479"},{"categoryCode":"5","masterCode":"3901000","code":"3906086","name":"BARANGAY 480"},{"categoryCode":"5","masterCode":"3901000","code":"3906087","name":"BARANGAY 481"},{"categoryCode":"5","masterCode":"3901000","code":"3906088","name":"BARANGAY 482"},{"categoryCode":"5","masterCode":"3901000","code":"3906089","name":"BARANGAY 483"},{"categoryCode":"5","masterCode":"3901000","code":"3906090","name":"BARANGAY 484"},{"categoryCode":"5","masterCode":"3901000","code":"3906091","name":"BARANGAY 485"},{"categoryCode":"5","masterCode":"3901000","code":"3906092","name":"BARANGAY 486"},{"categoryCode":"5","masterCode":"3901000","code":"3906093","name":"BARANGAY 487"},{"categoryCode":"5","masterCode":"3901000","code":"3906094","name":"BARANGAY 488"},{"categoryCode":"5","masterCode":"3901000","code":"3906095","name":"BARANGAY 489"},{"categoryCode":"5","masterCode":"3901000","code":"3906096","name":"BARANGAY 490"},{"categoryCode":"5","masterCode":"3901000","code":"3906097","name":"BARANGAY 491"},{"categoryCode":"5","masterCode":"3901000","code":"3906098","name":"BARANGAY 492"},{"categoryCode":"5","masterCode":"3901000","code":"3906099","name":"BARANGAY 493"},{"categoryCode":"5","masterCode":"3901000","code":"3906100","name":"BARANGAY 494"},{"categoryCode":"5","masterCode":"3901000","code":"3906101","name":"BARANGAY 495"},{"categoryCode":"5","masterCode":"3901000","code":"3906102","name":"BARANGAY 496"},{"categoryCode":"5","masterCode":"3901000","code":"3906103","name":"BARANGAY 497"},{"categoryCode":"5","masterCode":"3901000","code":"3906104","name":"BARANGAY 498"},{"categoryCode":"5","masterCode":"3901000","code":"3906105","name":"BARANGAY 499"},{"categoryCode":"5","masterCode":"3901000","code":"3906106","name":"BARANGAY 500"},{"categoryCode":"5","masterCode":"3901000","code":"3906107","name":"BARANGAY 501"},{"categoryCode":"5","masterCode":"3901000","code":"3906108","name":"BARANGAY 502"},{"categoryCode":"5","masterCode":"3901000","code":"3906109","name":"BARANGAY 503"},{"categoryCode":"5","masterCode":"3901000","code":"3906110","name":"BARANGAY 504"},{"categoryCode":"5","masterCode":"3901000","code":"3906111","name":"BARANGAY 505"},{"categoryCode":"5","masterCode":"3901000","code":"3906112","name":"BARANGAY 506"},{"categoryCode":"5","masterCode":"3901000","code":"3906113","name":"BARANGAY 507"},{"categoryCode":"5","masterCode":"3901000","code":"3906114","name":"BARANGAY 508"},{"categoryCode":"5","masterCode":"3901000","code":"3906115","name":"BARANGAY 509"},{"categoryCode":"5","masterCode":"3901000","code":"3906116","name":"BARANGAY 510"},{"categoryCode":"5","masterCode":"3901000","code":"3906117","name":"BARANGAY 511"},{"categoryCode":"5","masterCode":"3901000","code":"3906118","name":"BARANGAY 512"},{"categoryCode":"5","masterCode":"3901000","code":"3906119","name":"BARANGAY 513"},{"categoryCode":"5","masterCode":"3901000","code":"3906120","name":"BARANGAY 514"},{"categoryCode":"5","masterCode":"3901000","code":"3906121","name":"BARANGAY 515"},{"categoryCode":"5","masterCode":"3901000","code":"3906122","name":"BARANGAY 516"},{"categoryCode":"5","masterCode":"3901000","code":"3906123","name":"BARANGAY 517"},{"categoryCode":"5","masterCode":"3901000","code":"3906124","name":"BARANGAY 518"},{"categoryCode":"5","masterCode":"3901000","code":"3906125","name":"BARANGAY 519"},{"categoryCode":"5","masterCode":"3901000","code":"3906126","name":"BARANGAY 520"},{"categoryCode":"5","masterCode":"3901000","code":"3906127","name":"BARANGAY 521"},{"categoryCode":"5","masterCode":"3901000","code":"3906128","name":"BARANGAY 522"},{"categoryCode":"5","masterCode":"3901000","code":"3906129","name":"BARANGAY 523"},{"categoryCode":"5","masterCode":"3901000","code":"3906130","name":"BARANGAY 524"},{"categoryCode":"5","masterCode":"3901000","code":"3906131","name":"BARANGAY 525"},{"categoryCode":"5","masterCode":"3901000","code":"3906132","name":"BARANGAY 526"},{"categoryCode":"5","masterCode":"3901000","code":"3906133","name":"BARANGAY 527"},{"categoryCode":"5","masterCode":"3901000","code":"3906134","name":"BARANGAY 528"},{"categoryCode":"5","masterCode":"3901000","code":"3906135","name":"BARANGAY 529"},{"categoryCode":"5","masterCode":"3901000","code":"3906136","name":"BARANGAY 530"},{"categoryCode":"5","masterCode":"3901000","code":"3906137","name":"BARANGAY 531"},{"categoryCode":"5","masterCode":"3901000","code":"3906138","name":"BARANGAY 532"},{"categoryCode":"5","masterCode":"3901000","code":"3906139","name":"BARANGAY 533"},{"categoryCode":"5","masterCode":"3901000","code":"3906140","name":"BARANGAY 534"},{"categoryCode":"5","masterCode":"3901000","code":"3906141","name":"BARANGAY 535"},{"categoryCode":"5","masterCode":"3901000","code":"3906142","name":"BARANGAY 536"},{"categoryCode":"5","masterCode":"3901000","code":"3906143","name":"BARANGAY 537"},{"categoryCode":"5","masterCode":"3901000","code":"3906144","name":"BARANGAY 538"},{"categoryCode":"5","masterCode":"3901000","code":"3906145","name":"BARANGAY 539"},{"categoryCode":"5","masterCode":"3901000","code":"3906146","name":"BARANGAY 540"},{"categoryCode":"5","masterCode":"3901000","code":"3906147","name":"BARANGAY 541"},{"categoryCode":"5","masterCode":"3901000","code":"3906148","name":"BARANGAY 542"},{"categoryCode":"5","masterCode":"3901000","code":"3906149","name":"BARANGAY 543"},{"categoryCode":"5","masterCode":"3901000","code":"3906150","name":"BARANGAY 544"},{"categoryCode":"5","masterCode":"3901000","code":"3906151","name":"BARANGAY 545"},{"categoryCode":"5","masterCode":"3901000","code":"3906152","name":"BARANGAY 546"},{"categoryCode":"5","masterCode":"3901000","code":"3906153","name":"BARANGAY 547"},{"categoryCode":"5","masterCode":"3901000","code":"3906154","name":"BARANGAY 548"},{"categoryCode":"5","masterCode":"3901000","code":"3906155","name":"BARANGAY 549"},{"categoryCode":"5","masterCode":"3901000","code":"3906156","name":"BARANGAY 550"},{"categoryCode":"5","masterCode":"3901000","code":"3906157","name":"BARANGAY 551"},{"categoryCode":"5","masterCode":"3901000","code":"3906158","name":"BARANGAY 552"},{"categoryCode":"5","masterCode":"3901000","code":"3906159","name":"BARANGAY 553"},{"categoryCode":"5","masterCode":"3901000","code":"3906160","name":"BARANGAY 554"},{"categoryCode":"5","masterCode":"3901000","code":"3906161","name":"BARANGAY 555"},{"categoryCode":"5","masterCode":"3901000","code":"3906162","name":"BARANGAY 556"},{"categoryCode":"5","masterCode":"3901000","code":"3906163","name":"BARANGAY 557"},{"categoryCode":"5","masterCode":"3901000","code":"3906164","name":"BARANGAY 558"},{"categoryCode":"5","masterCode":"3901000","code":"3906165","name":"BARANGAY 559"},{"categoryCode":"5","masterCode":"3901000","code":"3906166","name":"BARANGAY 560"},{"categoryCode":"5","masterCode":"3901000","code":"3906167","name":"BARANGAY 561"},{"categoryCode":"5","masterCode":"3901000","code":"3906168","name":"BARANGAY 562"},{"categoryCode":"5","masterCode":"3901000","code":"3906169","name":"BARANGAY 563"},{"categoryCode":"5","masterCode":"3901000","code":"3906170","name":"BARANGAY 564"},{"categoryCode":"5","masterCode":"3901000","code":"3906171","name":"BARANGAY 565"},{"categoryCode":"5","masterCode":"3901000","code":"3906172","name":"BARANGAY 566"},{"categoryCode":"5","masterCode":"3901000","code":"3906173","name":"BARANGAY 567"},{"categoryCode":"5","masterCode":"3901000","code":"3906174","name":"BARANGAY 568"},{"categoryCode":"5","masterCode":"3901000","code":"3906175","name":"BARANGAY 569"},{"categoryCode":"5","masterCode":"3901000","code":"3906176","name":"BARANGAY 570"},{"categoryCode":"5","masterCode":"3901000","code":"3906177","name":"BARANGAY 571"},{"categoryCode":"5","masterCode":"3901000","code":"3906178","name":"BARANGAY 572"},{"categoryCode":"5","masterCode":"3901000","code":"3906179","name":"BARANGAY 573"},{"categoryCode":"5","masterCode":"3901000","code":"3906180","name":"BARANGAY 574"},{"categoryCode":"5","masterCode":"3901000","code":"3906181","name":"BARANGAY 575"},{"categoryCode":"5","masterCode":"3901000","code":"3906182","name":"BARANGAY 576"},{"categoryCode":"5","masterCode":"3901000","code":"3906183","name":"BARANGAY 577"},{"categoryCode":"5","masterCode":"3901000","code":"3906184","name":"BARANGAY 578"},{"categoryCode":"5","masterCode":"3901000","code":"3906185","name":"BARANGAY 579"},{"categoryCode":"5","masterCode":"3901000","code":"3906186","name":"BARANGAY 580"},{"categoryCode":"5","masterCode":"3901000","code":"3906187","name":"BARANGAY 581"},{"categoryCode":"5","masterCode":"3901000","code":"3906188","name":"BARANGAY 582"},{"categoryCode":"5","masterCode":"3901000","code":"3906189","name":"BARANGAY 583"},{"categoryCode":"5","masterCode":"3901000","code":"3906190","name":"BARANGAY 584"},{"categoryCode":"5","masterCode":"3901000","code":"3906191","name":"BARANGAY 585"},{"categoryCode":"5","masterCode":"3901000","code":"3906192","name":"BARANGAY 586 "},{"categoryCode":"5","masterCode":"3901000","code":"3906193","name":"BARANGAY 587 "},{"categoryCode":"5","masterCode":"3901000","code":"3906194","name":"BARANGAY 587-A"},{"categoryCode":"5","masterCode":"3901000","code":"3906195","name":"BARANGAY 588"},{"categoryCode":"5","masterCode":"3901000","code":"3906196","name":"BARANGAY 589"},{"categoryCode":"5","masterCode":"3901000","code":"3906197","name":"BARANGAY 590"},{"categoryCode":"5","masterCode":"3901000","code":"3906198","name":"BARANGAY 591"},{"categoryCode":"5","masterCode":"3901000","code":"3906199","name":"BARANGAY 592"},{"categoryCode":"5","masterCode":"3901000","code":"3906200","name":"BARANGAY 593"},{"categoryCode":"5","masterCode":"3901000","code":"3906201","name":"BARANGAY 594"},{"categoryCode":"5","masterCode":"3901000","code":"3906202","name":"BARANGAY 595"},{"categoryCode":"5","masterCode":"3901000","code":"3906203","name":"BARANGAY 596"},{"categoryCode":"5","masterCode":"3901000","code":"3906204","name":"BARANGAY 597"},{"categoryCode":"5","masterCode":"3901000","code":"3906205","name":"BARANGAY 598"},{"categoryCode":"5","masterCode":"3901000","code":"3906206","name":"BARANGAY 599"},{"categoryCode":"5","masterCode":"3901000","code":"3906207","name":"BARANGAY 600"},{"categoryCode":"5","masterCode":"3901000","code":"3906208","name":"BARANGAY 601"},{"categoryCode":"5","masterCode":"3901000","code":"3906209","name":"BARANGAY 602"},{"categoryCode":"5","masterCode":"3901000","code":"3906210","name":"BARANGAY 603"},{"categoryCode":"5","masterCode":"3901000","code":"3906211","name":"BARANGAY 604"},{"categoryCode":"5","masterCode":"3901000","code":"3906212","name":"BARANGAY 605"},{"categoryCode":"5","masterCode":"3901000","code":"3906213","name":"BARANGAY 606"},{"categoryCode":"5","masterCode":"3901000","code":"3906214","name":"BARANGAY 607"},{"categoryCode":"5","masterCode":"3901000","code":"3906215","name":"BARANGAY 608"},{"categoryCode":"5","masterCode":"3901000","code":"3906216","name":"BARANGAY 609"},{"categoryCode":"5","masterCode":"3901000","code":"3906217","name":"BARANGAY 610"},{"categoryCode":"5","masterCode":"3901000","code":"3906218","name":"BARANGAY 611"},{"categoryCode":"5","masterCode":"3901000","code":"3906219","name":"BARANGAY 612"},{"categoryCode":"5","masterCode":"3901000","code":"3906220","name":"BARANGAY 613"},{"categoryCode":"5","masterCode":"3901000","code":"3906221","name":"BARANGAY 614"},{"categoryCode":"5","masterCode":"3901000","code":"3906222","name":"BARANGAY 615"},{"categoryCode":"5","masterCode":"3901000","code":"3906223","name":"BARANGAY 616"},{"categoryCode":"5","masterCode":"3901000","code":"3906224","name":"BARANGAY 617"},{"categoryCode":"5","masterCode":"3901000","code":"3906225","name":"BARANGAY 618"},{"categoryCode":"5","masterCode":"3901000","code":"3906226","name":"BARANGAY 619"},{"categoryCode":"5","masterCode":"3901000","code":"3906227","name":"BARANGAY 620"},{"categoryCode":"5","masterCode":"3901000","code":"3906228","name":"BARANGAY 621"},{"categoryCode":"5","masterCode":"3901000","code":"3906229","name":"BARANGAY 622"},{"categoryCode":"5","masterCode":"3901000","code":"3906230","name":"BARANGAY 623"},{"categoryCode":"5","masterCode":"3901000","code":"3906231","name":"BARANGAY 624"},{"categoryCode":"5","masterCode":"3901000","code":"3906232","name":"BARANGAY 625"},{"categoryCode":"5","masterCode":"3901000","code":"3906233","name":"BARANGAY 626"},{"categoryCode":"5","masterCode":"3901000","code":"3906234","name":"BARANGAY 627"},{"categoryCode":"5","masterCode":"3901000","code":"3906235","name":"BARANGAY 628"},{"categoryCode":"5","masterCode":"3901000","code":"3906236","name":"BARANGAY 629"},{"categoryCode":"5","masterCode":"3901000","code":"3906237","name":"BARANGAY 630"},{"categoryCode":"5","masterCode":"3901000","code":"3906238","name":"BARANGAY 631"},{"categoryCode":"5","masterCode":"3901000","code":"3906239","name":"BARANGAY 632"},{"categoryCode":"5","masterCode":"3901000","code":"3906240","name":"BARANGAY 633"},{"categoryCode":"5","masterCode":"3901000","code":"3906241","name":"BARANGAY 634"},{"categoryCode":"5","masterCode":"3901000","code":"3906242","name":"BARANGAY 635"},{"categoryCode":"5","masterCode":"3901000","code":"3906243","name":"BARANGAY 636"},{"categoryCode":"5","masterCode":"3901000","code":"3907001","name":"BARANGAY 637"},{"categoryCode":"5","masterCode":"3901000","code":"3907002","name":"BARANGAY 638"},{"categoryCode":"5","masterCode":"3901000","code":"3907003","name":"BARANGAY 639"},{"categoryCode":"5","masterCode":"3901000","code":"3907004","name":"BARANGAY 640"},{"categoryCode":"5","masterCode":"3901000","code":"3907005","name":"BARANGAY 641"},{"categoryCode":"5","masterCode":"3901000","code":"3907006","name":"BARANGAY 642"},{"categoryCode":"5","masterCode":"3901000","code":"3907007","name":"BARANGAY 643"},{"categoryCode":"5","masterCode":"3901000","code":"3907008","name":"BARANGAY 644"},{"categoryCode":"5","masterCode":"3901000","code":"3907009","name":"BARANGAY 645"},{"categoryCode":"5","masterCode":"3901000","code":"3907010","name":"BARANGAY 646"},{"categoryCode":"5","masterCode":"3901000","code":"3907011","name":"BARANGAY 647"},{"categoryCode":"5","masterCode":"3901000","code":"3907012","name":"BARANGAY 648"},{"categoryCode":"5","masterCode":"3901000","code":"3908001","name":"BARANGAY 659"},{"categoryCode":"5","masterCode":"3901000","code":"3908002","name":"BARANGAY 659-A"},{"categoryCode":"5","masterCode":"3901000","code":"3908003","name":"BARANGAY 660"},{"categoryCode":"5","masterCode":"3901000","code":"3908004","name":"BARANGAY 660-A"},{"categoryCode":"5","masterCode":"3901000","code":"3908005","name":"BARANGAY 661"},{"categoryCode":"5","masterCode":"3901000","code":"3908008","name":"BARANGAY 666"},{"categoryCode":"5","masterCode":"3901000","code":"3908009","name":"BARANGAY 667"},{"categoryCode":"5","masterCode":"3901000","code":"3908010","name":"BARANGAY 668"},{"categoryCode":"5","masterCode":"3901000","code":"3908011","name":"BARANGAY 669"},{"categoryCode":"5","masterCode":"3901000","code":"3908012","name":"BARANGAY 670"},{"categoryCode":"5","masterCode":"3901000","code":"3908013","name":"BARANGAY 663"},{"categoryCode":"5","masterCode":"3901000","code":"3908014","name":"BARANGAY 663-A"},{"categoryCode":"5","masterCode":"3901000","code":"3908015","name":"BARANGAY 664"},{"categoryCode":"5","masterCode":"3901000","code":"3909001","name":"BARANGAY 654"},{"categoryCode":"5","masterCode":"3901000","code":"3909002","name":"BARANGAY 655"},{"categoryCode":"5","masterCode":"3901000","code":"3909003","name":"BARANGAY 656"},{"categoryCode":"5","masterCode":"3901000","code":"3909004","name":"BARANGAY 657"},{"categoryCode":"5","masterCode":"3901000","code":"3909005","name":"BARANGAY 658"},{"categoryCode":"5","masterCode":"3901000","code":"3910004","name":"BARANGAY 689"},{"categoryCode":"5","masterCode":"3901000","code":"3910005","name":"BARANGAY 690"},{"categoryCode":"5","masterCode":"3901000","code":"3910006","name":"BARANGAY 691"},{"categoryCode":"5","masterCode":"3901000","code":"3910007","name":"BARANGAY 692"},{"categoryCode":"5","masterCode":"3901000","code":"3910008","name":"BARANGAY 693"},{"categoryCode":"5","masterCode":"3901000","code":"3910009","name":"BARANGAY 694"},{"categoryCode":"5","masterCode":"3901000","code":"3910010","name":"BARANGAY 695"},{"categoryCode":"5","masterCode":"3901000","code":"3910011","name":"BARANGAY 696"},{"categoryCode":"5","masterCode":"3901000","code":"3910012","name":"BARANGAY 697"},{"categoryCode":"5","masterCode":"3901000","code":"3910013","name":"BARANGAY 698"},{"categoryCode":"5","masterCode":"3901000","code":"3910014","name":"BARANGAY 699"},{"categoryCode":"5","masterCode":"3901000","code":"3910015","name":"BARANGAY 700"},{"categoryCode":"5","masterCode":"3901000","code":"3910016","name":"BARANGAY 701"},{"categoryCode":"5","masterCode":"3901000","code":"3910017","name":"BARANGAY 702"},{"categoryCode":"5","masterCode":"3901000","code":"3910018","name":"BARANGAY 703"},{"categoryCode":"5","masterCode":"3901000","code":"3910019","name":"BARANGAY 704"},{"categoryCode":"5","masterCode":"3901000","code":"3910020","name":"BARANGAY 705"},{"categoryCode":"5","masterCode":"3901000","code":"3910021","name":"BARANGAY 706"},{"categoryCode":"5","masterCode":"3901000","code":"3910022","name":"BARANGAY 707"},{"categoryCode":"5","masterCode":"3901000","code":"3910023","name":"BARANGAY 708"},{"categoryCode":"5","masterCode":"3901000","code":"3910024","name":"BARANGAY 709"},{"categoryCode":"5","masterCode":"3901000","code":"3910025","name":"BARANGAY 710"},{"categoryCode":"5","masterCode":"3901000","code":"3910026","name":"BARANGAY 711"},{"categoryCode":"5","masterCode":"3901000","code":"3910027","name":"BARANGAY 712"},{"categoryCode":"5","masterCode":"3901000","code":"3910028","name":"BARANGAY 713"},{"categoryCode":"5","masterCode":"3901000","code":"3910029","name":"BARANGAY 714"},{"categoryCode":"5","masterCode":"3901000","code":"3910030","name":"BARANGAY 715"},{"categoryCode":"5","masterCode":"3901000","code":"3910031","name":"BARANGAY 716"},{"categoryCode":"5","masterCode":"3901000","code":"3910032","name":"BARANGAY 717"},{"categoryCode":"5","masterCode":"3901000","code":"3910033","name":"BARANGAY 718"},{"categoryCode":"5","masterCode":"3901000","code":"3910034","name":"BARANGAY 719"},{"categoryCode":"5","masterCode":"3901000","code":"3910035","name":"BARANGAY 720"},{"categoryCode":"5","masterCode":"3901000","code":"3910036","name":"BARANGAY 721"},{"categoryCode":"5","masterCode":"3901000","code":"3910037","name":"BARANGAY 722"},{"categoryCode":"5","masterCode":"3901000","code":"3910038","name":"BARANGAY 723"},{"categoryCode":"5","masterCode":"3901000","code":"3910039","name":"BARANGAY 724"},{"categoryCode":"5","masterCode":"3901000","code":"3910040","name":"BARANGAY 725"},{"categoryCode":"5","masterCode":"3901000","code":"3910041","name":"BARANGAY 726"},{"categoryCode":"5","masterCode":"3901000","code":"3910042","name":"BARANGAY 727"},{"categoryCode":"5","masterCode":"3901000","code":"3910043","name":"BARANGAY 728"},{"categoryCode":"5","masterCode":"3901000","code":"3910044","name":"BARANGAY 729"},{"categoryCode":"5","masterCode":"3901000","code":"3910045","name":"BARANGAY 730"},{"categoryCode":"5","masterCode":"3901000","code":"3910046","name":"BARANGAY 731"},{"categoryCode":"5","masterCode":"3901000","code":"3910047","name":"BARANGAY 732"},{"categoryCode":"5","masterCode":"3901000","code":"3910048","name":"BARANGAY 733"},{"categoryCode":"5","masterCode":"3901000","code":"3910052","name":"BARANGAY 738"},{"categoryCode":"5","masterCode":"3901000","code":"3910053","name":"BARANGAY 739"},{"categoryCode":"5","masterCode":"3901000","code":"3910054","name":"BARANGAY 740"},{"categoryCode":"5","masterCode":"3901000","code":"3910055","name":"BARANGAY 741"},{"categoryCode":"5","masterCode":"3901000","code":"3910056","name":"BARANGAY 742"},{"categoryCode":"5","masterCode":"3901000","code":"3910057","name":"BARANGAY 743"},{"categoryCode":"5","masterCode":"3901000","code":"3910058","name":"BARANGAY 744"},{"categoryCode":"5","masterCode":"3901000","code":"3910059","name":"BARANGAY 688 "},{"categoryCode":"5","masterCode":"3901000","code":"3910060","name":"BARANGAY 735 "},{"categoryCode":"5","masterCode":"3901000","code":"3910061","name":"BARANGAY 736 "},{"categoryCode":"5","masterCode":"3901000","code":"3910062","name":"BARANGAY 737 "},{"categoryCode":"5","masterCode":"3901000","code":"3910063","name":"BARANGAY 734"},{"categoryCode":"5","masterCode":"3901000","code":"3911001","name":"BARANGAY 662"},{"categoryCode":"5","masterCode":"3901000","code":"3911004","name":"BARANGAY 664-A"},{"categoryCode":"5","masterCode":"3901000","code":"3911005","name":"BARANGAY 671"},{"categoryCode":"5","masterCode":"3901000","code":"3911006","name":"BARANGAY 672"},{"categoryCode":"5","masterCode":"3901000","code":"3911007","name":"BARANGAY 673"},{"categoryCode":"5","masterCode":"3901000","code":"3911008","name":"BARANGAY 674"},{"categoryCode":"5","masterCode":"3901000","code":"3911009","name":"BARANGAY 675"},{"categoryCode":"5","masterCode":"3901000","code":"3911010","name":"BARANGAY 676"},{"categoryCode":"5","masterCode":"3901000","code":"3911011","name":"BARANGAY 677"},{"categoryCode":"5","masterCode":"3901000","code":"3911012","name":"BARANGAY 678"},{"categoryCode":"5","masterCode":"3901000","code":"3911013","name":"BARANGAY 679"},{"categoryCode":"5","masterCode":"3901000","code":"3911014","name":"BARANGAY 680"},{"categoryCode":"5","masterCode":"3901000","code":"3911015","name":"BARANGAY 681"},{"categoryCode":"5","masterCode":"3901000","code":"3911016","name":"BARANGAY 682"},{"categoryCode":"5","masterCode":"3901000","code":"3911017","name":"BARANGAY 683"},{"categoryCode":"5","masterCode":"3901000","code":"3911018","name":"BARANGAY 684 "},{"categoryCode":"5","masterCode":"3901000","code":"3911019","name":"BARANGAY 685"},{"categoryCode":"5","masterCode":"3901000","code":"3911023","name":"BARANGAY 809"},{"categoryCode":"5","masterCode":"3901000","code":"3911024","name":"BARANGAY 810"},{"categoryCode":"5","masterCode":"3901000","code":"3911025","name":"BARANGAY 811"},{"categoryCode":"5","masterCode":"3901000","code":"3911026","name":"BARANGAY 812"},{"categoryCode":"5","masterCode":"3901000","code":"3911027","name":"BARANGAY 813"},{"categoryCode":"5","masterCode":"3901000","code":"3911028","name":"BARANGAY 814"},{"categoryCode":"5","masterCode":"3901000","code":"3911029","name":"BARANGAY 815"},{"categoryCode":"5","masterCode":"3901000","code":"3911030","name":"BARANGAY 816"},{"categoryCode":"5","masterCode":"3901000","code":"3911031","name":"BARANGAY 817"},{"categoryCode":"5","masterCode":"3901000","code":"3911032","name":"BARANGAY 818"},{"categoryCode":"5","masterCode":"3901000","code":"3911034","name":"BARANGAY 819"},{"categoryCode":"5","masterCode":"3901000","code":"3911035","name":"BARANGAY 820"},{"categoryCode":"5","masterCode":"3901000","code":"3911036","name":"BARANGAY 821"},{"categoryCode":"5","masterCode":"3901000","code":"3911037","name":"BARANGAY 822"},{"categoryCode":"5","masterCode":"3901000","code":"3911038","name":"BARANGAY 823"},{"categoryCode":"5","masterCode":"3901000","code":"3911039","name":"BARANGAY 824"},{"categoryCode":"5","masterCode":"3901000","code":"3911040","name":"BARANGAY 825"},{"categoryCode":"5","masterCode":"3901000","code":"3911041","name":"BARANGAY 826"},{"categoryCode":"5","masterCode":"3901000","code":"3911042","name":"BARANGAY 827"},{"categoryCode":"5","masterCode":"3901000","code":"3911043","name":"BARANGAY 828"},{"categoryCode":"5","masterCode":"3901000","code":"3911044","name":"BARANGAY 829 "},{"categoryCode":"5","masterCode":"3901000","code":"3911045","name":"BARANGAY 830 "},{"categoryCode":"5","masterCode":"3901000","code":"3911046","name":"BARANGAY 831 "},{"categoryCode":"5","masterCode":"3901000","code":"3911047","name":"BARANGAY 832 "},{"categoryCode":"5","masterCode":"3901000","code":"3911048","name":"BARANGAY 686 "},{"categoryCode":"5","masterCode":"3901000","code":"3911049","name":"BARANGAY 687 "},{"categoryCode":"5","masterCode":"3901000","code":"3912001","name":"BARANGAY 833"},{"categoryCode":"5","masterCode":"3901000","code":"3912002","name":"BARANGAY 834"},{"categoryCode":"5","masterCode":"3901000","code":"3912003","name":"BARANGAY 835"},{"categoryCode":"5","masterCode":"3901000","code":"3912004","name":"BARANGAY 836"},{"categoryCode":"5","masterCode":"3901000","code":"3912005","name":"BARANGAY 837"},{"categoryCode":"5","masterCode":"3901000","code":"3912006","name":"BARANGAY 838"},{"categoryCode":"5","masterCode":"3901000","code":"3912007","name":"BARANGAY 839"},{"categoryCode":"5","masterCode":"3901000","code":"3912008","name":"BARANGAY 840"},{"categoryCode":"5","masterCode":"3901000","code":"3912009","name":"BARANGAY 841"},{"categoryCode":"5","masterCode":"3901000","code":"3912010","name":"BARANGAY 842"},{"categoryCode":"5","masterCode":"3901000","code":"3912011","name":"BARANGAY 843"},{"categoryCode":"5","masterCode":"3901000","code":"3912012","name":"BARANGAY 844"},{"categoryCode":"5","masterCode":"3901000","code":"3912013","name":"BARANGAY 845"},{"categoryCode":"5","masterCode":"3901000","code":"3912014","name":"BARANGAY 846"},{"categoryCode":"5","masterCode":"3901000","code":"3912015","name":"BARANGAY 847"},{"categoryCode":"5","masterCode":"3901000","code":"3912016","name":"BARANGAY 848"},{"categoryCode":"5","masterCode":"3901000","code":"3912017","name":"BARANGAY 849"},{"categoryCode":"5","masterCode":"3901000","code":"3912018","name":"BARANGAY 850"},{"categoryCode":"5","masterCode":"3901000","code":"3912019","name":"BARANGAY 851"},{"categoryCode":"5","masterCode":"3901000","code":"3912020","name":"BARANGAY 852"},{"categoryCode":"5","masterCode":"3901000","code":"3912021","name":"BARANGAY 853"},{"categoryCode":"5","masterCode":"3901000","code":"3912023","name":"BARANGAY 855"},{"categoryCode":"5","masterCode":"3901000","code":"3912024","name":"BARANGAY 856"},{"categoryCode":"5","masterCode":"3901000","code":"3912025","name":"BARANGAY 857"},{"categoryCode":"5","masterCode":"3901000","code":"3912026","name":"BARANGAY 858"},{"categoryCode":"5","masterCode":"3901000","code":"3912027","name":"BARANGAY 859"},{"categoryCode":"5","masterCode":"3901000","code":"3912028","name":"BARANGAY 860"},{"categoryCode":"5","masterCode":"3901000","code":"3912029","name":"BARANGAY 861"},{"categoryCode":"5","masterCode":"3901000","code":"3912030","name":"BARANGAY 862"},{"categoryCode":"5","masterCode":"3901000","code":"3912031","name":"BARANGAY 863"},{"categoryCode":"5","masterCode":"3901000","code":"3912032","name":"BARANGAY 864"},{"categoryCode":"5","masterCode":"3901000","code":"3912033","name":"BARANGAY 865"},{"categoryCode":"5","masterCode":"3901000","code":"3912034","name":"BARANGAY 867"},{"categoryCode":"5","masterCode":"3901000","code":"3912035","name":"BARANGAY 868"},{"categoryCode":"5","masterCode":"3901000","code":"3912036","name":"BARANGAY 870"},{"categoryCode":"5","masterCode":"3901000","code":"3912037","name":"BARANGAY 871"},{"categoryCode":"5","masterCode":"3901000","code":"3912038","name":"BARANGAY 872"},{"categoryCode":"5","masterCode":"3901000","code":"3912039","name":"BARANGAY 869"},{"categoryCode":"5","masterCode":"3901000","code":"3913001","name":"BARANGAY 649"},{"categoryCode":"5","masterCode":"3901000","code":"3913002","name":"BARANGAY 650"},{"categoryCode":"5","masterCode":"3901000","code":"3913003","name":"BARANGAY 651"},{"categoryCode":"5","masterCode":"3901000","code":"3913004","name":"BARANGAY 652"},{"categoryCode":"5","masterCode":"3901000","code":"3913005","name":"BARANGAY 653"},{"categoryCode":"5","masterCode":"3901000","code":"3914002","name":"BARANGAY 745"},{"categoryCode":"5","masterCode":"3901000","code":"3914003","name":"BARANGAY 746"},{"categoryCode":"5","masterCode":"3901000","code":"3914004","name":"BARANGAY 747"},{"categoryCode":"5","masterCode":"3901000","code":"3914005","name":"BARANGAY 748"},{"categoryCode":"5","masterCode":"3901000","code":"3914006","name":"BARANGAY 749"},{"categoryCode":"5","masterCode":"3901000","code":"3914007","name":"BARANGAY 750"},{"categoryCode":"5","masterCode":"3901000","code":"3914008","name":"BARANGAY 751"},{"categoryCode":"5","masterCode":"3901000","code":"3914009","name":"BARANGAY 752"},{"categoryCode":"5","masterCode":"3901000","code":"3914010","name":"BARANGAY 753"},{"categoryCode":"5","masterCode":"3901000","code":"3914011","name":"BARANGAY 755"},{"categoryCode":"5","masterCode":"3901000","code":"3914012","name":"BARANGAY 756"},{"categoryCode":"5","masterCode":"3901000","code":"3914013","name":"BARANGAY 757"},{"categoryCode":"5","masterCode":"3901000","code":"3914014","name":"BARANGAY 758"},{"categoryCode":"5","masterCode":"3901000","code":"3914015","name":"BARANGAY 759"},{"categoryCode":"5","masterCode":"3901000","code":"3914016","name":"BARANGAY 760"},{"categoryCode":"5","masterCode":"3901000","code":"3914017","name":"BARANGAY 761"},{"categoryCode":"5","masterCode":"3901000","code":"3914018","name":"BARANGAY 762"},{"categoryCode":"5","masterCode":"3901000","code":"3914019","name":"BARANGAY 763"},{"categoryCode":"5","masterCode":"3901000","code":"3914020","name":"BARANGAY 764"},{"categoryCode":"5","masterCode":"3901000","code":"3914021","name":"BARANGAY 765"},{"categoryCode":"5","masterCode":"3901000","code":"3914022","name":"BARANGAY 766"},{"categoryCode":"5","masterCode":"3901000","code":"3914023","name":"BARANGAY 767"},{"categoryCode":"5","masterCode":"3901000","code":"3914024","name":"BARANGAY 768"},{"categoryCode":"5","masterCode":"3901000","code":"3914025","name":"BARANGAY 769"},{"categoryCode":"5","masterCode":"3901000","code":"3914026","name":"BARANGAY 770"},{"categoryCode":"5","masterCode":"3901000","code":"3914027","name":"BARANGAY 771"},{"categoryCode":"5","masterCode":"3901000","code":"3914028","name":"BARANGAY 772"},{"categoryCode":"5","masterCode":"3901000","code":"3914029","name":"BARANGAY 773"},{"categoryCode":"5","masterCode":"3901000","code":"3914030","name":"BARANGAY 774"},{"categoryCode":"5","masterCode":"3901000","code":"3914031","name":"BARANGAY 775"},{"categoryCode":"5","masterCode":"3901000","code":"3914032","name":"BARANGAY 776"},{"categoryCode":"5","masterCode":"3901000","code":"3914033","name":"BARANGAY 777"},{"categoryCode":"5","masterCode":"3901000","code":"3914034","name":"BARANGAY 778"},{"categoryCode":"5","masterCode":"3901000","code":"3914035","name":"BARANGAY 779"},{"categoryCode":"5","masterCode":"3901000","code":"3914036","name":"BARANGAY 780"},{"categoryCode":"5","masterCode":"3901000","code":"3914037","name":"BARANGAY 781"},{"categoryCode":"5","masterCode":"3901000","code":"3914038","name":"BARANGAY 782"},{"categoryCode":"5","masterCode":"3901000","code":"3914039","name":"BARANGAY 783"},{"categoryCode":"5","masterCode":"3901000","code":"3914040","name":"BARANGAY 784"},{"categoryCode":"5","masterCode":"3901000","code":"3914041","name":"BARANGAY 785"},{"categoryCode":"5","masterCode":"3901000","code":"3914042","name":"BARANGAY 786"},{"categoryCode":"5","masterCode":"3901000","code":"3914043","name":"BARANGAY 787"},{"categoryCode":"5","masterCode":"3901000","code":"3914044","name":"BARANGAY 788"},{"categoryCode":"5","masterCode":"3901000","code":"3914045","name":"BARANGAY 789"},{"categoryCode":"5","masterCode":"3901000","code":"3914046","name":"BARANGAY 790"},{"categoryCode":"5","masterCode":"3901000","code":"3914047","name":"BARANGAY 791"},{"categoryCode":"5","masterCode":"3901000","code":"3914048","name":"BARANGAY 792"},{"categoryCode":"5","masterCode":"3901000","code":"3914049","name":"BARANGAY 793"},{"categoryCode":"5","masterCode":"3901000","code":"3914050","name":"BARANGAY 794"},{"categoryCode":"5","masterCode":"3901000","code":"3914051","name":"BARANGAY 795"},{"categoryCode":"5","masterCode":"3901000","code":"3914052","name":"BARANGAY 796"},{"categoryCode":"5","masterCode":"3901000","code":"3914053","name":"BARANGAY 797"},{"categoryCode":"5","masterCode":"3901000","code":"3914054","name":"BARANGAY 798"},{"categoryCode":"5","masterCode":"3901000","code":"3914055","name":"BARANGAY 799"},{"categoryCode":"5","masterCode":"3901000","code":"3914056","name":"BARANGAY 800"},{"categoryCode":"5","masterCode":"3901000","code":"3914057","name":"BARANGAY 801"},{"categoryCode":"5","masterCode":"3901000","code":"3914058","name":"BARANGAY 802"},{"categoryCode":"5","masterCode":"3901000","code":"3914059","name":"BARANGAY 803"},{"categoryCode":"5","masterCode":"3901000","code":"3914060","name":"BARANGAY 804"},{"categoryCode":"5","masterCode":"3901000","code":"3914061","name":"BARANGAY 805"},{"categoryCode":"5","masterCode":"3901000","code":"3914062","name":"BARANGAY 806"},{"categoryCode":"5","masterCode":"3901000","code":"3914063","name":"BARANGAY 807"},{"categoryCode":"5","masterCode":"3901000","code":"3914064","name":"BARANGAY 866"},{"categoryCode":"5","masterCode":"3901000","code":"3914066","name":"BARANGAY 873"},{"categoryCode":"5","masterCode":"3901000","code":"3914067","name":"BARANGAY 874"},{"categoryCode":"5","masterCode":"3901000","code":"3914068","name":"BARANGAY 875"},{"categoryCode":"5","masterCode":"3901000","code":"3914069","name":"BARANGAY 876"},{"categoryCode":"5","masterCode":"3901000","code":"3914070","name":"BARANGAY 877"},{"categoryCode":"5","masterCode":"3901000","code":"3914071","name":"BARANGAY 878"},{"categoryCode":"5","masterCode":"3901000","code":"3914072","name":"BARANGAY 879"},{"categoryCode":"5","masterCode":"3901000","code":"3914073","name":"BARANGAY 880"},{"categoryCode":"5","masterCode":"3901000","code":"3914074","name":"BARANGAY 881"},{"categoryCode":"5","masterCode":"3901000","code":"3914075","name":"BARANGAY 882"},{"categoryCode":"5","masterCode":"3901000","code":"3914076","name":"BARANGAY 883"},{"categoryCode":"5","masterCode":"3901000","code":"3914077","name":"BARANGAY 884"},{"categoryCode":"5","masterCode":"3901000","code":"3914078","name":"BARANGAY 885"},{"categoryCode":"5","masterCode":"3901000","code":"3914079","name":"BARANGAY 886"},{"categoryCode":"5","masterCode":"3901000","code":"3914080","name":"BARANGAY 887"},{"categoryCode":"5","masterCode":"3901000","code":"3914081","name":"BARANGAY 888"},{"categoryCode":"5","masterCode":"3901000","code":"3914082","name":"BARANGAY 889"},{"categoryCode":"5","masterCode":"3901000","code":"3914083","name":"BARANGAY 890"},{"categoryCode":"5","masterCode":"3901000","code":"3914084","name":"BARANGAY 891"},{"categoryCode":"5","masterCode":"3901000","code":"3914085","name":"BARANGAY 892"},{"categoryCode":"5","masterCode":"3901000","code":"3914086","name":"BARANGAY 893"},{"categoryCode":"5","masterCode":"3901000","code":"3914087","name":"BARANGAY 894"},{"categoryCode":"5","masterCode":"3901000","code":"3914088","name":"BARANGAY 895"},{"categoryCode":"5","masterCode":"3901000","code":"3914089","name":"BARANGAY 896"},{"categoryCode":"5","masterCode":"3901000","code":"3914090","name":"BARANGAY 897"},{"categoryCode":"5","masterCode":"3901000","code":"3914091","name":"BARANGAY 898"},{"categoryCode":"5","masterCode":"3901000","code":"3914092","name":"BARANGAY 899"},{"categoryCode":"5","masterCode":"3901000","code":"3914093","name":"BARANGAY 900"},{"categoryCode":"5","masterCode":"3901000","code":"3914094","name":"BARANGAY 901"},{"categoryCode":"5","masterCode":"3901000","code":"3914095","name":"BARANGAY 902"},{"categoryCode":"5","masterCode":"3901000","code":"3914096","name":"BARANGAY 903"},{"categoryCode":"5","masterCode":"3901000","code":"3914097","name":"BARANGAY 904"},{"categoryCode":"5","masterCode":"3901000","code":"3914098","name":"BARANGAY 905"},{"categoryCode":"5","masterCode":"3901000","code":"3914099","name":"BARANGAY 754"},{"categoryCode":"5","masterCode":"3901000","code":"3914100","name":"BARANGAY 808"},{"categoryCode":"5","masterCode":"3901000","code":"3914101","name":"BARANGAY 818-A"}]}