{"regions":[{"categoryCode":"5","masterCode":"0607000","code":"0607001","name":"ABACA"},{"categoryCode":"5","masterCode":"0607000","code":"0607002","name":"ARAS-ASAN"},{"categoryCode":"5","masterCode":"0607000","code":"0607003","name":"AROBO"},{"categoryCode":"5","masterCode":"0607000","code":"0607004","name":"ATABAY"},{"categoryCode":"5","masterCode":"0607000","code":"0607005","name":"ATIOTES"},{"categoryCode":"5","masterCode":"0607000","code":"0607006","name":"BAGUMBAYAN"},{"categoryCode":"5","masterCode":"0607000","code":"0607007","name":"BALLESCAS"},{"categoryCode":"5","masterCode":"0607000","code":"0607008","name":"BALUD"},{"categoryCode":"5","masterCode":"0607000","code":"0607009","name":"BARASANAN A"},{"categoryCode":"5","masterCode":"0607000","code":"0607010","name":"BARASANAN B"},{"categoryCode":"5","masterCode":"0607000","code":"0607011","name":"BARASANAN C"},{"categoryCode":"5","masterCode":"0607000","code":"0607012","name":"BARIRI"},{"categoryCode":"5","masterCode":"0607000","code":"0607013","name":"CAMANDAGAN"},{"categoryCode":"5","masterCode":"0607000","code":"0607014","name":"CATO-OGAN"},{"categoryCode":"5","masterCode":"0607000","code":"0607015","name":"DANAWAN"},{"categoryCode":"5","masterCode":"0607000","code":"0607016","name":"DICLUM"},{"categoryCode":"5","masterCode":"0607000","code":"0607017","name":"FATIMA"},{"categoryCode":"5","masterCode":"0607000","code":"0607018","name":"GAMAD"},{"categoryCode":"5","masterCode":"0607000","code":"0607019","name":"IGBALOGO"},{"categoryCode":"5","masterCode":"0607000","code":"0607020","name":"IGBANGCAL-A"},{"categoryCode":"5","masterCode":"0607000","code":"0607021","name":"IGBANGCAL-B"},{"categoryCode":"5","masterCode":"0607000","code":"0607022","name":"IGBANGCAL-C"},{"categoryCode":"5","masterCode":"0607000","code":"0607023","name":"IGCABUAD"},{"categoryCode":"5","masterCode":"0607000","code":"0607024","name":"IGCADO"},{"categoryCode":"5","masterCode":"0607000","code":"0607025","name":"IGCALAWAGAN"},{"categoryCode":"5","masterCode":"0607000","code":"0607026","name":"IGCAPUYAS"},{"categoryCode":"5","masterCode":"0607000","code":"0607027","name":"IGCASICAD"},{"categoryCode":"5","masterCode":"0607000","code":"0607028","name":"IGDALAGUIT"},{"categoryCode":"5","masterCode":"0607000","code":"0607029","name":"IGDANLOG"},{"categoryCode":"5","masterCode":"0607000","code":"0607030","name":"IGDURAROG"},{"categoryCode":"5","masterCode":"0607000","code":"0607031","name":"IGTUGAS"},{"categoryCode":"5","masterCode":"0607000","code":"0607032","name":"LAWIGAN"},{"categoryCode":"5","masterCode":"0607000","code":"0607033","name":"MANALING"},{"categoryCode":"5","masterCode":"0607000","code":"0607034","name":"MASAYO"},{"categoryCode":"5","masterCode":"0607000","code":"0607035","name":"NAGSUBUAN"},{"categoryCode":"5","masterCode":"0607000","code":"0607036","name":"PACIENCIA"},{"categoryCode":"5","masterCode":"0607000","code":"0607037","name":"POBLACION NORTE"},{"categoryCode":"5","masterCode":"0607000","code":"0607038","name":"POBLACION SUR"},{"categoryCode":"5","masterCode":"0607000","code":"0607039","name":"PORTILLO"},{"categoryCode":"5","masterCode":"0607000","code":"0607040","name":"QUEZON"},{"categoryCode":"5","masterCode":"0607000","code":"0607041","name":"OPSAN"},{"categoryCode":"5","masterCode":"0607000","code":"0607042","name":"NASULI-A"},{"categoryCode":"5","masterCode":"0607000","code":"0607043","name":"SAMALAGUE"},{"categoryCode":"5","masterCode":"0607000","code":"0607044","name":"STO. TOMAS"},{"categoryCode":"5","masterCode":"0607000","code":"0607045","name":"TACBUYAN"},{"categoryCode":"5","masterCode":"0607000","code":"0607046","name":"TENE"},{"categoryCode":"5","masterCode":"0607000","code":"0607047","name":"VILLAFLOR "},{"categoryCode":"5","masterCode":"0607000","code":"0607048","name":"YSULAT"},{"categoryCode":"5","masterCode":"0607000","code":"0607049","name":"IGCADAC"},{"categoryCode":"5","masterCode":"0607000","code":"0607050","name":"LINDERO"}]}