{"regions":[{"categoryCode":"5","masterCode":"4501000","code":"4501001","name":"ALANGILAN"},{"categoryCode":"5","masterCode":"4501000","code":"4501002","name":"ALIJIS"},{"categoryCode":"5","masterCode":"4501000","code":"4501003","name":"BANAGO"},{"categoryCode":"5","masterCode":"4501000","code":"4501004","name":"BARANGAY 1 "},{"categoryCode":"5","masterCode":"4501000","code":"4501005","name":"BARANGAY 10 "},{"categoryCode":"5","masterCode":"4501000","code":"4501006","name":"BARANGAY 11 "},{"categoryCode":"5","masterCode":"4501000","code":"4501007","name":"BARANGAY 12 "},{"categoryCode":"5","masterCode":"4501000","code":"4501008","name":"BARANGAY 13 "},{"categoryCode":"5","masterCode":"4501000","code":"4501009","name":"BARANGAY 14 "},{"categoryCode":"5","masterCode":"4501000","code":"4501010","name":"BARANGAY 15 "},{"categoryCode":"5","masterCode":"4501000","code":"4501011","name":"BARANGAY 16 "},{"categoryCode":"5","masterCode":"4501000","code":"4501012","name":"BARANGAY 17 "},{"categoryCode":"5","masterCode":"4501000","code":"4501013","name":"BARANGAY 18 "},{"categoryCode":"5","masterCode":"4501000","code":"4501014","name":"BARANGAY 19 "},{"categoryCode":"5","masterCode":"4501000","code":"4501015","name":"BARANGAY 2 "},{"categoryCode":"5","masterCode":"4501000","code":"4501016","name":"BARANGAY 20 "},{"categoryCode":"5","masterCode":"4501000","code":"4501017","name":"BARANGAY 21 "},{"categoryCode":"5","masterCode":"4501000","code":"4501018","name":"BARANGAY 22 "},{"categoryCode":"5","masterCode":"4501000","code":"4501019","name":"BARANGAY 23 "},{"categoryCode":"5","masterCode":"4501000","code":"4501020","name":"BARANGAY 24 "},{"categoryCode":"5","masterCode":"4501000","code":"4501021","name":"BARANGAY 25 "},{"categoryCode":"5","masterCode":"4501000","code":"4501022","name":"BARANGAY 26 "},{"categoryCode":"5","masterCode":"4501000","code":"4501023","name":"BARANGAY 27 "},{"categoryCode":"5","masterCode":"4501000","code":"4501024","name":"BARANGAY 28 "},{"categoryCode":"5","masterCode":"4501000","code":"4501025","name":"BARANGAY 29 "},{"categoryCode":"5","masterCode":"4501000","code":"4501026","name":"BARANGAY 3 "},{"categoryCode":"5","masterCode":"4501000","code":"4501027","name":"BARANGAY 30 "},{"categoryCode":"5","masterCode":"4501000","code":"4501028","name":"BARANGAY 31 "},{"categoryCode":"5","masterCode":"4501000","code":"4501029","name":"BARANGAY 32 "},{"categoryCode":"5","masterCode":"4501000","code":"4501030","name":"BARANGAY 33 "},{"categoryCode":"5","masterCode":"4501000","code":"4501031","name":"BARANGAY 34 "},{"categoryCode":"5","masterCode":"4501000","code":"4501032","name":"BARANGAY 35 "},{"categoryCode":"5","masterCode":"4501000","code":"4501033","name":"BARANGAY 36 "},{"categoryCode":"5","masterCode":"4501000","code":"4501034","name":"BARANGAY 37 "},{"categoryCode":"5","masterCode":"4501000","code":"4501035","name":"BARANGAY 38 "},{"categoryCode":"5","masterCode":"4501000","code":"4501036","name":"BARANGAY 39 "},{"categoryCode":"5","masterCode":"4501000","code":"4501037","name":"BARANGAY 4 "},{"categoryCode":"5","masterCode":"4501000","code":"4501038","name":"BARANGAY 40 "},{"categoryCode":"5","masterCode":"4501000","code":"4501039","name":"BARANGAY 41 "},{"categoryCode":"5","masterCode":"4501000","code":"4501040","name":"BARANGAY 5 "},{"categoryCode":"5","masterCode":"4501000","code":"4501041","name":"BARANGAY 6 "},{"categoryCode":"5","masterCode":"4501000","code":"4501042","name":"BARANGAY 7 "},{"categoryCode":"5","masterCode":"4501000","code":"4501043","name":"BARANGAY 8 "},{"categoryCode":"5","masterCode":"4501000","code":"4501044","name":"BARANGAY 9 "},{"categoryCode":"5","masterCode":"4501000","code":"4501045","name":"BATA"},{"categoryCode":"5","masterCode":"4501000","code":"4501046","name":"CABUG"},{"categoryCode":"5","masterCode":"4501000","code":"4501047","name":"ESTEFANIA"},{"categoryCode":"5","masterCode":"4501000","code":"4501048","name":"FELISA"},{"categoryCode":"5","masterCode":"4501000","code":"4501049","name":"GRANADA"},{"categoryCode":"5","masterCode":"4501000","code":"4501050","name":"MANDALAGAN"},{"categoryCode":"5","masterCode":"4501000","code":"4501051","name":"MANSILINGAN"},{"categoryCode":"5","masterCode":"4501000","code":"4501052","name":"MONTEVISTA"},{"categoryCode":"5","masterCode":"4501000","code":"4501053","name":"PAHANOCOY"},{"categoryCode":"5","masterCode":"4501000","code":"4501054","name":"PUNTA TAYTAY"},{"categoryCode":"5","masterCode":"4501000","code":"4501055","name":"SINGCANG-AIRPORT"},{"categoryCode":"5","masterCode":"4501000","code":"4501056","name":"SUM-AG"},{"categoryCode":"5","masterCode":"4501000","code":"4501057","name":"TACULING"},{"categoryCode":"5","masterCode":"4501000","code":"4501058","name":"TANGUB"},{"categoryCode":"5","masterCode":"4501000","code":"4501059","name":"VILLAMONTE"},{"categoryCode":"5","masterCode":"4501000","code":"4501060","name":"VISTA ALEGRE"},{"categoryCode":"5","masterCode":"4501000","code":"4501061","name":"HANDUMANAN"}]}