{"regions":[{"categoryCode":null,"masterCode":null,"code":"46060054","name":"46060054"},{"categoryCode":null,"masterCode":null,"code":"46060055","name":"46060055"},{"categoryCode":null,"masterCode":null,"code":"46060056","name":"46060056"},{"categoryCode":null,"masterCode":null,"code":"46060057","name":"46060057"},{"categoryCode":null,"masterCode":null,"code":"46060058","name":"46060058"},{"categoryCode":null,"masterCode":null,"code":"46060059","name":"46060059"},{"categoryCode":null,"masterCode":null,"code":"46060060","name":"46060060"},{"categoryCode":null,"masterCode":null,"code":"46060061","name":"46060061"}]}