{"regions":[{"categoryCode":null,"masterCode":null,"code":"63030154","name":"63030154"},{"categoryCode":null,"masterCode":null,"code":"63030155","name":"63030155"},{"categoryCode":null,"masterCode":null,"code":"63030156","name":"63030156"},{"categoryCode":null,"masterCode":null,"code":"63030157","name":"63030157"},{"categoryCode":null,"masterCode":null,"code":"63030158","name":"63030158"},{"categoryCode":null,"masterCode":null,"code":"63030159","name":"63030159"},{"categoryCode":null,"masterCode":null,"code":"63030160","name":"63030160"},{"categoryCode":null,"masterCode":null,"code":"63030161","name":"63030161"},{"categoryCode":null,"masterCode":null,"code":"63030162","name":"63030162"},{"categoryCode":null,"masterCode":null,"code":"63030163","name":"63030163"},{"categoryCode":null,"masterCode":null,"code":"63030164","name":"63030164"},{"categoryCode":null,"masterCode":null,"code":"63030165","name":"63030165"},{"categoryCode":null,"masterCode":null,"code":"63030166","name":"63030166"},{"categoryCode":null,"masterCode":null,"code":"63030167","name":"63030167"}]}