{"regions":[{"categoryCode":null,"masterCode":null,"code":"34030011","name":"34030011"},{"categoryCode":null,"masterCode":null,"code":"34030012","name":"34030012"},{"categoryCode":null,"masterCode":null,"code":"34030013","name":"34030013"},{"categoryCode":null,"masterCode":null,"code":"34030014","name":"34030014"},{"categoryCode":null,"masterCode":null,"code":"34030015","name":"34030015"},{"categoryCode":null,"masterCode":null,"code":"34030016","name":"34030016"},{"categoryCode":null,"masterCode":null,"code":"34030017","name":"34030017"},{"categoryCode":null,"masterCode":null,"code":"34030018","name":"34030018"},{"categoryCode":null,"masterCode":null,"code":"34030019","name":"34030019"},{"categoryCode":null,"masterCode":null,"code":"34030020","name":"34030020"},{"categoryCode":null,"masterCode":null,"code":"34030021","name":"34030021"},{"categoryCode":null,"masterCode":null,"code":"34030022","name":"34030022"},{"categoryCode":null,"masterCode":null,"code":"34030023","name":"34030023"},{"categoryCode":null,"masterCode":null,"code":"34030024","name":"34030024"},{"categoryCode":null,"masterCode":null,"code":"34030025","name":"34030025"},{"categoryCode":null,"masterCode":null,"code":"34030026","name":"34030026"},{"categoryCode":null,"masterCode":null,"code":"34030027","name":"34030027"}]}