{"regions":[{"categoryCode":"5","masterCode":"1214000","code":"1214001","name":"BACANI"},{"categoryCode":"5","masterCode":"1214000","code":"1214002","name":"BOGTONGBOD"},{"categoryCode":"5","masterCode":"1214000","code":"1214003","name":"BONBON"},{"categoryCode":"5","masterCode":"1214000","code":"1214004","name":"BONTUD"},{"categoryCode":"5","masterCode":"1214000","code":"1214005","name":"BUACAO"},{"categoryCode":"5","masterCode":"1214000","code":"1214006","name":"BUANGAN"},{"categoryCode":"5","masterCode":"1214000","code":"1214007","name":"CABOG"},{"categoryCode":"5","masterCode":"1214000","code":"1214008","name":"CABOY"},{"categoryCode":"5","masterCode":"1214000","code":"1214009","name":"CALUWASAN"},{"categoryCode":"5","masterCode":"1214000","code":"1214010","name":"CANDAJEC"},{"categoryCode":"5","masterCode":"1214000","code":"1214011","name":"CANTOYOC"},{"categoryCode":"5","masterCode":"1214000","code":"1214012","name":"COMAANG"},{"categoryCode":"5","masterCode":"1214000","code":"1214013","name":"DANAHAO"},{"categoryCode":"5","masterCode":"1214000","code":"1214014","name":"KATIPUNAN"},{"categoryCode":"5","masterCode":"1214000","code":"1214015","name":"LAJOG"},{"categoryCode":"5","masterCode":"1214000","code":"1214016","name":"MATAUB"},{"categoryCode":"5","masterCode":"1214000","code":"1214017","name":"NAHAWAN"},{"categoryCode":"5","masterCode":"1214000","code":"1214018","name":"POBLACION CENTRO"},{"categoryCode":"5","masterCode":"1214000","code":"1214019","name":"POBLACION NORTE"},{"categoryCode":"5","masterCode":"1214000","code":"1214020","name":"POBLACION SUR"},{"categoryCode":"5","masterCode":"1214000","code":"1214021","name":"TANGARAN"},{"categoryCode":"5","masterCode":"1214000","code":"1214022","name":"TONTUNAN"},{"categoryCode":"5","masterCode":"1214000","code":"1214023","name":"TUBOD"},{"categoryCode":"5","masterCode":"1214000","code":"1214024","name":"VILLAFLOR"}]}