{"regions":[{"categoryCode":"5","masterCode":"2407000","code":"2407001","name":"BACUNGAN"},{"categoryCode":"5","masterCode":"2407000","code":"2407002","name":"BALNATE"},{"categoryCode":"5","masterCode":"2407000","code":"2407003","name":"BARAYONG"},{"categoryCode":"5","masterCode":"2407000","code":"2407004","name":"BLOCON"},{"categoryCode":"5","masterCode":"2407000","code":"2407005","name":"DALAWINON"},{"categoryCode":"5","masterCode":"2407000","code":"2407006","name":"DALUMAY"},{"categoryCode":"5","masterCode":"2407000","code":"2407007","name":"GLAMANG"},{"categoryCode":"5","masterCode":"2407000","code":"2407008","name":"KANAPULO"},{"categoryCode":"5","masterCode":"2407000","code":"2407009","name":"KASUGA"},{"categoryCode":"5","masterCode":"2407000","code":"2407010","name":"LOWER BALA"},{"categoryCode":"5","masterCode":"2407000","code":"2407011","name":"MABINI"},{"categoryCode":"5","masterCode":"2407000","code":"2407012","name":"MALAWANIT"},{"categoryCode":"5","masterCode":"2407000","code":"2407013","name":"MALONGON"},{"categoryCode":"5","masterCode":"2407000","code":"2407014","name":"NEW ILOCOS"},{"categoryCode":"5","masterCode":"2407000","code":"2407015","name":"POBLACION"},{"categoryCode":"5","masterCode":"2407000","code":"2407016","name":"SAN ISIDRO"},{"categoryCode":"5","masterCode":"2407000","code":"2407017","name":"SAN MIGUEL"},{"categoryCode":"5","masterCode":"2407000","code":"2407018","name":"TACUL"},{"categoryCode":"5","masterCode":"2407000","code":"2407019","name":"TAGAYTAY"},{"categoryCode":"5","masterCode":"2407000","code":"2407020","name":"UPPER BALA"},{"categoryCode":"5","masterCode":"2407000","code":"2407021","name":"MAIBO"},{"categoryCode":"5","masterCode":"2407000","code":"2407022","name":"NEW OPON"}]}